Workbook
Name ALPINE: #REF!
Name ALPINE: #REF!
Name ALTWEISS: #REF!
Name ALTWEISS: #REF!
Name BLANCO: #REF!
Name BLANCO: #REF!
Name BLANCO_: #REF!
Name BLANCO_: #REF!
Name CIELO3: INDIRECT(' CIELORRASO EXT'!$C$3)
Name CIELO3: INDIRECT('[1] CIELORRASO INT '!$C$3)
Name CIELO3: INDIRECT(#REF!)
Name CIELORASO: INDIRECT(' CIELORRASO EXT'!$C$3)
Name CIELORASO: INDIRECT('[1] CIELORRASO INT '!$C$3)
Name CIELORASO: INDIRECT(#REF!)
Name CIELORASO2: INDIRECT(' CIELORRASO EXT'!$C$3)
Name CIELORASO2: INDIRECT('[1] CIELORRASO INT '!$C$3)
Name CIELORASO2: INDIRECT(#REF!)
Name CIELORASO5: INDIRECT(' CIELORRASO EXT'!$C$3)
Name CIELORASO5: INDIRECT('[1] CIELORRASO INT '!$C$3)
Name CIELORASO5: INDIRECT(#REF!)
Name COLOR: INDIRECT('[1]WALL PANELS EXT'!$C$5)
Name COLOR: INDIRECT('[1]WALL PANELS EXT'!$C$5)
Name COLOR: INDIRECT(#REF!)
Name CONCRET_C: #REF!
Name CONCRET_C: #REF!
Name CONCRET_C_: #REF!
Name CONCRET_C_: #REF!
Name CONCRET_WITE: #REF!
Name CONCRET_WITE: #REF!
Name CONCRET_WITE_: #REF!
Name CONCRET_WITE_: #REF!
Name EUCALIPTUS: #REF!
Name EUCALIPTUS: #REF!
Name EUCALIPTUS_: #REF!
Name EUCALIPTUS_: #REF!
Name EUCALYPTUS: #REF!
Name EUCALYPTUS: #REF!
Name foil: INDIRECT('[1]WALL PANELS EXT'!$C$5)
Name foil: INDIRECT('[1]WALL PANELS EXT'!$C$5)
Name foil: INDIRECT(#REF!)
Name foil2: INDIRECT('[1]WALL PANELS EXT'!$F$5)
Name foil2: INDIRECT('[1]WALL PANELS EXT'!$F$5)
Name foil2: INDIRECT(#REF!)
Name foil3: INDIRECT('[1] WALL PANELLS INT'!$C$5)
Name foil3: INDIRECT('[1] WALL PANELLS INT'!$C$5)
Name foil3: INDIRECT(#REF!)
Name FOIL4: INDIRECT('[1] WALL PANELLS INT'!$C$5)
Name FOIL4: INDIRECT('[1] WALL PANELLS INT'!$C$5)
Name FOIL4: INDIRECT(#REF!)
Name FOIL5: INDIRECT('[1] WALL PANELLS INT'!$C$5)
Name FOIL5: INDIRECT('[1] WALL PANELLS INT'!$C$5)
Name FOIL5: INDIRECT(#REF!)
Name foil6: INDIRECT('[1] WALL PANELLS INT'!$F$5)
Name foil6: INDIRECT('[1] WALL PANELLS INT'!$F$5)
Name foil6: INDIRECT(#REF!)
Name GOLDBRONZE: #REF!
Name GOLDBRONZE: #REF!
Name GOLDEN_OK: #REF!
Name GOLDEN_OK: #REF!
Name GOLDENOK: #REF!

Sheet PLANILLA PEDIDO
C2: DESCUENTOS | E2: DESCUENTOS | G2: DESCUENTOS | J2: =+TODAY() -> 46148
B3: PERFILES PVC | C3: 0 | D3: WALL PANELS | E3: 0 | F3: PISOS | G3: 0
B4: REFUERZOS | C4: 0 | D4: CIELORASO | E4: 0 | F4: DECKS | G4: 0
B5: ACCESORIOS | C5: 0 | D5: TUBULARES | E5: 0 | F5: ZOCALOS | G5: 0 | J5: vers. 2
B7: Cliente: | K7: PLANILLA PEDIDO NAC. MAYO 2026
B8: Obra / Referencia: | K8: SUB TOTAL | L8: =SUM(L11:L123) -> 0
B10: Codigo | C10: Cantidad | D10: Descripcion | E10: Masa | F10: Color | G10: Unitario en u$s | H10: Presentacion ML / UN | L10: Total en u$s
D11: =IFERROR(VLOOKUP(B11,'TARIFA MASTER'!$B$5:$C$3741,2,0),0) -> 0 | E11: =IFERROR(VLOOKUP(B11,'TARIFA MASTER'!B10:L3462,3,0),0) -> 0 | F11: =IFERROR(VLOOKUP(B11,'TARIFA MASTER'!$B$15:$E$3702,4,0),0) -> 0 | G11: =IFERROR(VLOOKUP(B11,'TARIFA MASTER'!$B$5:$L$4699,11,0),0) -> 0 | H11: =IFERROR(VLOOKUP(B11,'TARIFA MASTER'!$B$5:$J$3754,5,0),0) -> 0 | K11: =IFERROR(VLOOKUP(B11,'TARIFA MASTER'!$B$5:$G$3752,6,0),0) -> 0 | L11: =+G11*C11 -> 0 | M11: =IFERROR(VLOOKUP(B11,[2]PESOS!A$2:D$3072,4,0),0) -> 0 | N11: =+M11*C11 -> 0
D12: =IFERROR(VLOOKUP(B12,'TARIFA MASTER'!$B$5:$C$3741,2,0),0) -> 0 | E12: =IFERROR(VLOOKUP(B12,'TARIFA MASTER'!B11:L3463,3,0),0) -> 0 | F12: =IFERROR(VLOOKUP(B12,'TARIFA MASTER'!$B$15:$E$3702,4,0),0) -> 0 | G12: =IFERROR(VLOOKUP(B12,'TARIFA MASTER'!$B$5:$L$4699,11,0),0) -> 0 | H12: =IFERROR(VLOOKUP(B12,'TARIFA MASTER'!$B$5:$J$3754,5,0),0) -> 0 | K12: =IFERROR(VLOOKUP(B12,'TARIFA MASTER'!$B$5:$G$3752,6,0),0) -> 0 | L12: =+G12*C12 -> 0 | M12: =IFERROR(VLOOKUP(B12,[2]PESOS!A$2:D$3072,4,0),0) -> 0 | N12: =+M12*C12 -> 0
D13: =IFERROR(VLOOKUP(B13,'TARIFA MASTER'!$B$5:$C$3741,2,0),0) -> 0 | E13: =IFERROR(VLOOKUP(B13,'TARIFA MASTER'!B11:L3464,3,0),0) -> 0 | F13: =IFERROR(VLOOKUP(B13,'TARIFA MASTER'!$B$15:$E$3702,4,0),0) -> 0 | G13: =IFERROR(VLOOKUP(B13,'TARIFA MASTER'!$B$5:$L$4699,11,0),0) -> 0 | H13: =IFERROR(VLOOKUP(B13,'TARIFA MASTER'!$B$5:$J$3754,5,0),0) -> 0 | K13: =IFERROR(VLOOKUP(B13,'TARIFA MASTER'!$B$5:$G$3752,6,0),0) -> 0 | L13: =+G13*C13 -> 0 | M13: =IFERROR(VLOOKUP(B13,[2]PESOS!A$2:D$3072,4,0),0) -> 0 | N13: =+M13*C13 -> 0
D14: =IFERROR(VLOOKUP(B14,'TARIFA MASTER'!$B$5:$C$3741,2,0),0) -> 0 | E14: =IFERROR(VLOOKUP(B14,'TARIFA MASTER'!B11:L3465,3,0),0) -> 0 | F14: =IFERROR(VLOOKUP(B14,'TARIFA MASTER'!$B$15:$E$3702,4,0),0) -> 0 | G14: =IFERROR(VLOOKUP(B14,'TARIFA MASTER'!$B$5:$L$4699,11,0),0) -> 0 | H14: =IFERROR(VLOOKUP(B14,'TARIFA MASTER'!$B$5:$J$3754,5,0),0) -> 0 | K14: =IFERROR(VLOOKUP(B14,'TARIFA MASTER'!$B$5:$G$3752,6,0),0) -> 0 | L14: =+G14*C14 -> 0 | M14: =IFERROR(VLOOKUP(B14,[2]PESOS!A$2:D$3072,4,0),0) -> 0 | N14: =+M14*C14 -> 0
D15: =IFERROR(VLOOKUP(B15,'TARIFA MASTER'!$B$5:$C$3741,2,0),0) -> 0 | E15: =IFERROR(VLOOKUP(B15,'TARIFA MASTER'!B11:L3466,3,0),0) -> 0 | F15: =IFERROR(VLOOKUP(B15,'TARIFA MASTER'!$B$15:$E$3702,4,0),0) -> 0 | G15: =IFERROR(VLOOKUP(B15,'TARIFA MASTER'!$B$5:$L$4699,11,0),0) -> 0 | H15: =IFERROR(VLOOKUP(B15,'TARIFA MASTER'!$B$5:$J$3754,5,0),0) -> 0 | K15: =IFERROR(VLOOKUP(B15,'TARIFA MASTER'!$B$5:$G$3752,6,0),0) -> 0 | L15: =+G15*C15 -> 0 | M15: =IFERROR(VLOOKUP(B15,[2]PESOS!A$2:D$3072,4,0),0) -> 0 | N15: =+M15*C15 -> 0
D16: =IFERROR(VLOOKUP(B16,'TARIFA MASTER'!$B$5:$C$3741,2,0),0) -> 0 | E16: =IFERROR(VLOOKUP(B16,'TARIFA MASTER'!B12:L3467,3,0),0) -> 0 | F16: =IFERROR(VLOOKUP(B16,'TARIFA MASTER'!$B$15:$E$3702,4,0),0) -> 0 | G16: =IFERROR(VLOOKUP(B16,'TARIFA MASTER'!$B$5:$L$4699,11,0),0) -> 0 | H16: =IFERROR(VLOOKUP(B16,'TARIFA MASTER'!$B$5:$J$3754,5,0),0) -> 0 | K16: =IFERROR(VLOOKUP(B16,'TARIFA MASTER'!$B$5:$G$3752,6,0),0) -> 0 | L16: =+G16*C16 -> 0 | M16: =IFERROR(VLOOKUP(B16,[2]PESOS!A$2:D$3072,4,0),0) -> 0 | N16: =+M16*C16 -> 0
D17: =IFERROR(VLOOKUP(B17,'TARIFA MASTER'!$B$5:$C$3741,2,0),0) -> 0 | E17: =IFERROR(VLOOKUP(B17,'TARIFA MASTER'!B13:L3471,3,0),0) -> 0 | F17: =IFERROR(VLOOKUP(B17,'TARIFA MASTER'!$B$15:$E$3702,4,0),0) -> 0 | G17: =IFERROR(VLOOKUP(B17,'TARIFA MASTER'!$B$5:$L$4699,11,0),0) -> 0 | H17: =IFERROR(VLOOKUP(B17,'TARIFA MASTER'!$B$5:$J$3754,5,0),0) -> 0 | K17: =IFERROR(VLOOKUP(B17,'TARIFA MASTER'!$B$5:$G$3752,6,0),0) -> 0 | L17: =+G17*C17 -> 0
D18: =IFERROR(VLOOKUP(B18,'TARIFA MASTER'!$B$5:$C$3741,2,0),0) -> 0 | E18: =IFERROR(VLOOKUP(B18,'TARIFA MASTER'!B15:L3472,3,0),0) -> 0 | F18: =IFERROR(VLOOKUP(B18,'TARIFA MASTER'!$B$15:$E$3702,4,0),0) -> 0 | G18: =IFERROR(VLOOKUP(B18,'TARIFA MASTER'!$B$5:$L$4699,11,0),0) -> 0 | H18: =IFERROR(VLOOKUP(B18,'TARIFA MASTER'!$B$5:$J$3754,5,0),0) -> 0 | K18: =IFERROR(VLOOKUP(B18,'TARIFA MASTER'!$B$5:$G$3752,6,0),0) -> 0 | L18: =+G18*C18 -> 0
D19: =IFERROR(VLOOKUP(B19,'TARIFA MASTER'!$B$5:$C$3741,2,0),0) -> 0 | E19: =IFERROR(VLOOKUP(B19,'TARIFA MASTER'!B15:L3473,3,0),0) -> 0 | F19: =IFERROR(VLOOKUP(B19,'TARIFA MASTER'!$B$15:$E$3702,4,0),0) -> 0 | G19: =IFERROR(VLOOKUP(B19,'TARIFA MASTER'!$B$5:$L$4699,11,0),0) -> 0 | H19: =IFERROR(VLOOKUP(B19,'TARIFA MASTER'!$B$5:$J$3754,5,0),0) -> 0 | K19: =IFERROR(VLOOKUP(B19,'TARIFA MASTER'!$B$5:$G$3752,6,0),0) -> 0 | L19: =+G19*C19 -> 0
D20: =IFERROR(VLOOKUP(B20,'TARIFA MASTER'!$B$5:$C$3741,2,0),0) -> 0 | E20: =IFERROR(VLOOKUP(B20,'TARIFA MASTER'!B15:L3474,3,0),0) -> 0 | F20: =IFERROR(VLOOKUP(B20,'TARIFA MASTER'!$B$15:$E$3702,4,0),0) -> 0 | G20: =IFERROR(VLOOKUP(B20,'TARIFA MASTER'!$B$5:$L$4699,11,0),0) -> 0 | H20: =IFERROR(VLOOKUP(B20,'TARIFA MASTER'!$B$5:$J$3754,5,0),0) -> 0 | K20: =IFERROR(VLOOKUP(B20,'TARIFA MASTER'!$B$5:$G$3752,6,0),0) -> 0 | L20: =+G20*C20 -> 0
D21: =IFERROR(VLOOKUP(B21,'TARIFA MASTER'!$B$5:$C$3741,2,0),0) -> 0 | E21: =IFERROR(VLOOKUP(B21,'TARIFA MASTER'!B15:L3475,3,0),0) -> 0 | F21: =IFERROR(VLOOKUP(B21,'TARIFA MASTER'!$B$15:$E$3702,4,0),0) -> 0 | G21: =IFERROR(VLOOKUP(B21,'TARIFA MASTER'!$B$5:$L$4699,11,0),0) -> 0 | H21: =IFERROR(VLOOKUP(B21,'TARIFA MASTER'!$B$5:$J$3754,5,0),0) -> 0 | K21: =IFERROR(VLOOKUP(B21,'TARIFA MASTER'!$B$5:$G$3752,6,0),0) -> 0 | L21: =+G21*C21 -> 0
D22: =IFERROR(VLOOKUP(B22,'TARIFA MASTER'!$B$5:$C$3741,2,0),0) -> 0 | E22: =IFERROR(VLOOKUP(B22,'TARIFA MASTER'!B15:L3476,3,0),0) -> 0 | F22: =IFERROR(VLOOKUP(B22,'TARIFA MASTER'!$B$15:$E$3702,4,0),0) -> 0 | G22: =IFERROR(VLOOKUP(B22,'TARIFA MASTER'!$B$5:$L$4699,11,0),0) -> 0 | H22: =IFERROR(VLOOKUP(B22,'TARIFA MASTER'!$B$5:$J$3754,5,0),0) -> 0 | K22: =IFERROR(VLOOKUP(B22,'TARIFA MASTER'!$B$5:$G$3752,6,0),0) -> 0 | L22: =+G22*C22 -> 0
D23: =IFERROR(VLOOKUP(B23,'TARIFA MASTER'!$B$5:$C$3741,2,0),0) -> 0 | E23: =IFERROR(VLOOKUP(B23,'TARIFA MASTER'!B15:L3477,3,0),0) -> 0 | F23: =IFERROR(VLOOKUP(B23,'TARIFA MASTER'!$B$15:$E$3702,4,0),0) -> 0 | G23: =IFERROR(VLOOKUP(B23,'TARIFA MASTER'!$B$5:$L$4699,11,0),0) -> 0 | H23: =IFERROR(VLOOKUP(B23,'TARIFA MASTER'!$B$5:$J$3754,5,0),0) -> 0 | K23: =IFERROR(VLOOKUP(B23,'TARIFA MASTER'!$B$5:$G$3752,6,0),0) -> 0 | L23: =+G23*C23 -> 0
D24: =IFERROR(VLOOKUP(B24,'TARIFA MASTER'!$B$5:$C$3741,2,0),0) -> 0 | E24: =IFERROR(VLOOKUP(B24,'TARIFA MASTER'!B15:L3477,3,0),0) -> 0 | F24: =IFERROR(VLOOKUP(B24,'TARIFA MASTER'!$B$15:$E$3702,4,0),0) -> 0 | G24: =IFERROR(VLOOKUP(B24,'TARIFA MASTER'!$B$5:$L$4699,11,0),0) -> 0 | H24: =IFERROR(VLOOKUP(B24,'TARIFA MASTER'!$B$5:$J$3754,5,0),0) -> 0 | K24: =IFERROR(VLOOKUP(B24,'TARIFA MASTER'!$B$5:$G$3752,6,0),0) -> 0 | L24: =+G24*C24 -> 0
D25: =IFERROR(VLOOKUP(B25,'TARIFA MASTER'!$B$5:$C$3741,2,0),0) -> 0 | E25: =IFERROR(VLOOKUP(B25,'TARIFA MASTER'!B15:L3478,3,0),0) -> 0 | F25: =IFERROR(VLOOKUP(B25,'TARIFA MASTER'!$B$15:$E$3702,4,0),0) -> 0 | G25: =IFERROR(VLOOKUP(B25,'TARIFA MASTER'!$B$5:$L$4699,11,0),0) -> 0 | H25: =IFERROR(VLOOKUP(B25,'TARIFA MASTER'!$B$5:$J$3754,5,0),0) -> 0 | K25: =IFERROR(VLOOKUP(B25,'TARIFA MASTER'!$B$5:$G$3752,6,0),0) -> 0 | L25: =+G25*C25 -> 0
D26: =IFERROR(VLOOKUP(B26,'TARIFA MASTER'!$B$5:$C$3741,2,0),0) -> 0 | E26: =IFERROR(VLOOKUP(B26,'TARIFA MASTER'!B15:L3479,3,0),0) -> 0 | F26: =IFERROR(VLOOKUP(B26,'TARIFA MASTER'!$B$15:$E$3702,4,0),0) -> 0 | G26: =IFERROR(VLOOKUP(B26,'TARIFA MASTER'!$B$5:$L$4699,11,0),0) -> 0 | H26: =IFERROR(VLOOKUP(B26,'TARIFA MASTER'!$B$5:$J$3754,5,0),0) -> 0 | K26: =IFERROR(VLOOKUP(B26,'TARIFA MASTER'!$B$5:$G$3752,6,0),0) -> 0 | L26: =+G26*C26 -> 0
D27: =IFERROR(VLOOKUP(B27,'TARIFA MASTER'!$B$5:$C$3741,2,0),0) -> 0 | E27: =IFERROR(VLOOKUP(B27,'TARIFA MASTER'!B15:L3479,3,0),0) -> 0 | F27: =IFERROR(VLOOKUP(B27,'TARIFA MASTER'!$B$15:$E$3702,4,0),0) -> 0 | G27: =IFERROR(VLOOKUP(B27,'TARIFA MASTER'!$B$5:$L$4699,11,0),0) -> 0 | H27: =IFERROR(VLOOKUP(B27,'TARIFA MASTER'!$B$5:$J$3754,5,0),0) -> 0 | K27: =IFERROR(VLOOKUP(B27,'TARIFA MASTER'!$B$5:$G$3752,6,0),0) -> 0 | L27: =+G27*C27 -> 0
D28: =IFERROR(VLOOKUP(B28,'TARIFA MASTER'!$B$5:$C$3741,2,0),0) -> 0 | E28: =IFERROR(VLOOKUP(B28,'TARIFA MASTER'!B15:L3480,3,0),0) -> 0 | F28: =IFERROR(VLOOKUP(B28,'TARIFA MASTER'!$B$15:$E$3702,4,0),0) -> 0 | G28: =IFERROR(VLOOKUP(B28,'TARIFA MASTER'!$B$5:$L$4699,11,0),0) -> 0 | H28: =IFERROR(VLOOKUP(B28,'TARIFA MASTER'!$B$5:$J$3754,5,0),0) -> 0 | K28: =IFERROR(VLOOKUP(B28,'TARIFA MASTER'!$B$5:$G$3752,6,0),0) -> 0 | L28: =+G28*C28 -> 0
D29: =IFERROR(VLOOKUP(B29,'TARIFA MASTER'!$B$5:$C$3741,2,0),0) -> 0 | E29: =IFERROR(VLOOKUP(B29,'TARIFA MASTER'!B15:L3481,3,0),0) -> 0 | F29: =IFERROR(VLOOKUP(B29,'TARIFA MASTER'!$B$15:$E$3702,4,0),0) -> 0 | G29: =IFERROR(VLOOKUP(B29,'TARIFA MASTER'!$B$5:$L$4699,11,0),0) -> 0 | H29: =IFERROR(VLOOKUP(B29,'TARIFA MASTER'!$B$5:$J$3754,5,0),0) -> 0 | K29: =IFERROR(VLOOKUP(B29,'TARIFA MASTER'!$B$5:$G$3752,6,0),0) -> 0 | L29: =+G29*C29 -> 0
D30: =IFERROR(VLOOKUP(B30,'TARIFA MASTER'!$B$5:$C$3741,2,0),0) -> 0 | E30: =IFERROR(VLOOKUP(B30,'TARIFA MASTER'!B15:L3482,3,0),0) -> 0 | F30: =IFERROR(VLOOKUP(B30,'TARIFA MASTER'!$B$15:$E$3702,4,0),0) -> 0 | G30: =IFERROR(VLOOKUP(B30,'TARIFA MASTER'!$B$5:$L$4699,11,0),0) -> 0 | H30: =IFERROR(VLOOKUP(B30,'TARIFA MASTER'!$B$5:$J$3754,5,0),0) -> 0 | K30: =IFERROR(VLOOKUP(B30,'TARIFA MASTER'!$B$5:$G$3752,6,0),0) -> 0 | L30: =+G30*C30 -> 0
D31: =IFERROR(VLOOKUP(B31,'TARIFA MASTER'!$B$5:$C$3741,2,0),0) -> 0 | E31: =IFERROR(VLOOKUP(B31,'TARIFA MASTER'!B15:L3483,3,0),0) -> 0 | F31: =IFERROR(VLOOKUP(B31,'TARIFA MASTER'!$B$15:$E$3702,4,0),0) -> 0 | G31: =IFERROR(VLOOKUP(B31,'TARIFA MASTER'!$B$5:$L$4699,11,0),0) -> 0 | H31: =IFERROR(VLOOKUP(B31,'TARIFA MASTER'!$B$5:$J$3754,5,0),0) -> 0 | K31: =IFERROR(VLOOKUP(B31,'TARIFA MASTER'!$B$5:$G$3752,6,0),0) -> 0 | L31: =+G31*C31 -> 0
D32: =IFERROR(VLOOKUP(B32,'TARIFA MASTER'!$B$5:$C$3741,2,0),0) -> 0 | E32: =IFERROR(VLOOKUP(B32,'TARIFA MASTER'!B15:L3484,3,0),0) -> 0 | F32: =IFERROR(VLOOKUP(B32,'TARIFA MASTER'!$B$15:$E$3702,4,0),0) -> 0 | G32: =IFERROR(VLOOKUP(B32,'TARIFA MASTER'!$B$5:$L$4699,11,0),0) -> 0 | H32: =IFERROR(VLOOKUP(B32,'TARIFA MASTER'!$B$5:$J$3754,5,0),0) -> 0 | K32: =IFERROR(VLOOKUP(B32,'TARIFA MASTER'!$B$5:$G$3752,6,0),0) -> 0 | L32: =+G32*C32 -> 0
D33: =IFERROR(VLOOKUP(B33,'TARIFA MASTER'!$B$5:$C$3741,2,0),0) -> 0 | E33: =IFERROR(VLOOKUP(B33,'TARIFA MASTER'!B15:L3485,3,0),0) -> 0 | F33: =IFERROR(VLOOKUP(B33,'TARIFA MASTER'!$B$15:$E$3702,4,0),0) -> 0 | G33: =IFERROR(VLOOKUP(B33,'TARIFA MASTER'!$B$5:$L$4699,11,0),0) -> 0 | H33: =IFERROR(VLOOKUP(B33,'TARIFA MASTER'!$B$5:$J$3754,5,0),0) -> 0 | K33: =IFERROR(VLOOKUP(B33,'TARIFA MASTER'!$B$5:$G$3752,6,0),0) -> 0 | L33: =+G33*C33 -> 0
D34: =IFERROR(VLOOKUP(B34,'TARIFA MASTER'!$B$5:$C$3741,2,0),0) -> 0 | E34: =IFERROR(VLOOKUP(B34,'TARIFA MASTER'!B15:L3486,3,0),0) -> 0 | F34: =IFERROR(VLOOKUP(B34,'TARIFA MASTER'!$B$15:$E$3702,4,0),0) -> 0 | G34: =IFERROR(VLOOKUP(B34,'TARIFA MASTER'!$B$5:$L$4699,11,0),0) -> 0 | H34: =IFERROR(VLOOKUP(B34,'TARIFA MASTER'!$B$5:$J$3754,5,0),0) -> 0 | K34: =IFERROR(VLOOKUP(B34,'TARIFA MASTER'!$B$5:$G$3752,6,0),0) -> 0 | L34: =+G34*C34 -> 0
D35: =IFERROR(VLOOKUP(B35,'TARIFA MASTER'!$B$5:$C$3741,2,0),0) -> 0 | E35: =IFERROR(VLOOKUP(B35,'TARIFA MASTER'!B15:L3487,3,0),0) -> 0 | F35: =IFERROR(VLOOKUP(B35,'TARIFA MASTER'!$B$15:$E$3702,4,0),0) -> 0 | G35: =IFERROR(VLOOKUP(B35,'TARIFA MASTER'!$B$5:$L$4699,11,0),0) -> 0 | H35: =IFERROR(VLOOKUP(B35,'TARIFA MASTER'!$B$5:$J$3754,5,0),0) -> 0 | K35: =IFERROR(VLOOKUP(B35,'TARIFA MASTER'!$B$5:$G$3752,6,0),0) -> 0 | L35: =+G35*C35 -> 0
D36: =IFERROR(VLOOKUP(B36,'TARIFA MASTER'!$B$5:$C$3741,2,0),0) -> 0 | E36: =IFERROR(VLOOKUP(B36,'TARIFA MASTER'!B15:L3488,3,0),0) -> 0 | F36: =IFERROR(VLOOKUP(B36,'TARIFA MASTER'!$B$15:$E$3702,4,0),0) -> 0 | G36: =IFERROR(VLOOKUP(B36,'TARIFA MASTER'!$B$5:$L$4699,11,0),0) -> 0 | H36: =IFERROR(VLOOKUP(B36,'TARIFA MASTER'!$B$5:$J$3754,5,0),0) -> 0 | K36: =IFERROR(VLOOKUP(B36,'TARIFA MASTER'!$B$5:$G$3752,6,0),0) -> 0 | L36: =+G36*C36 -> 0
D37: =IFERROR(VLOOKUP(B37,'TARIFA MASTER'!$B$5:$C$3741,2,0),0) -> 0 | E37: =IFERROR(VLOOKUP(B37,'TARIFA MASTER'!B15:L3489,3,0),0) -> 0 | F37: =IFERROR(VLOOKUP(B37,'TARIFA MASTER'!$B$15:$E$3702,4,0),0) -> 0 | G37: =IFERROR(VLOOKUP(B37,'TARIFA MASTER'!$B$5:$L$4699,11,0),0) -> 0 | H37: =IFERROR(VLOOKUP(B37,'TARIFA MASTER'!$B$5:$J$3754,5,0),0) -> 0 | K37: =IFERROR(VLOOKUP(B37,'TARIFA MASTER'!$B$5:$G$3752,6,0),0) -> 0 | L37: =+G37*C37 -> 0
D38: =IFERROR(VLOOKUP(B38,'TARIFA MASTER'!$B$5:$C$3741,2,0),0) -> 0 | E38: =IFERROR(VLOOKUP(B38,'TARIFA MASTER'!B15:L3490,3,0),0) -> 0 | F38: =IFERROR(VLOOKUP(B38,'TARIFA MASTER'!$B$15:$E$3702,4,0),0) -> 0 | G38: =IFERROR(VLOOKUP(B38,'TARIFA MASTER'!$B$5:$L$4699,11,0),0) -> 0 | H38: =IFERROR(VLOOKUP(B38,'TARIFA MASTER'!$B$5:$J$3754,5,0),0) -> 0 | K38: =IFERROR(VLOOKUP(B38,'TARIFA MASTER'!$B$5:$G$3752,6,0),0) -> 0 | L38: =+G38*C38 -> 0
D39: =IFERROR(VLOOKUP(B39,'TARIFA MASTER'!$B$5:$C$3741,2,0),0) -> 0 | E39: =IFERROR(VLOOKUP(B39,'TARIFA MASTER'!B15:L3491,3,0),0) -> 0 | F39: =IFERROR(VLOOKUP(B39,'TARIFA MASTER'!$B$15:$E$3702,4,0),0) -> 0 | G39: =IFERROR(VLOOKUP(B39,'TARIFA MASTER'!$B$5:$L$4699,11,0),0) -> 0 | H39: =IFERROR(VLOOKUP(B39,'TARIFA MASTER'!$B$5:$J$3754,5,0),0) -> 0 | K39: =IFERROR(VLOOKUP(B39,'TARIFA MASTER'!$B$5:$G$3752,6,0),0) -> 0 | L39: =+G39*C39 -> 0
D40: =IFERROR(VLOOKUP(B40,'TARIFA MASTER'!$B$5:$C$3741,2,0),0) -> 0 | E40: =IFERROR(VLOOKUP(B40,'TARIFA MASTER'!B15:L3492,3,0),0) -> 0 | F40: =IFERROR(VLOOKUP(B40,'TARIFA MASTER'!$B$15:$E$3702,4,0),0) -> 0 | G40: =IFERROR(VLOOKUP(B40,'TARIFA MASTER'!$B$5:$L$4699,11,0),0) -> 0 | H40: =IFERROR(VLOOKUP(B40,'TARIFA MASTER'!$B$5:$J$3754,5,0),0) -> 0 | K40: =IFERROR(VLOOKUP(B40,'TARIFA MASTER'!$B$5:$G$3752,6,0),0) -> 0 | L40: =+G40*C40 -> 0
D41: =IFERROR(VLOOKUP(B41,'TARIFA MASTER'!$B$5:$C$3741,2,0),0) -> 0 | E41: =IFERROR(VLOOKUP(B41,'TARIFA MASTER'!B15:L3493,3,0),0) -> 0 | F41: =IFERROR(VLOOKUP(B41,'TARIFA MASTER'!$B$15:$E$3702,4,0),0) -> 0 | G41: =IFERROR(VLOOKUP(B41,'TARIFA MASTER'!$B$5:$L$4699,11,0),0) -> 0 | H41: =IFERROR(VLOOKUP(B41,'TARIFA MASTER'!$B$5:$J$3754,5,0),0) -> 0 | K41: =IFERROR(VLOOKUP(B41,'TARIFA MASTER'!$B$5:$G$3752,6,0),0) -> 0 | L41: =+G41*C41 -> 0
D42: =IFERROR(VLOOKUP(B42,'TARIFA MASTER'!$B$5:$C$3741,2,0),0) -> 0 | E42: =IFERROR(VLOOKUP(B42,'TARIFA MASTER'!B16:L3494,3,0),0) -> 0 | F42: =IFERROR(VLOOKUP(B42,'TARIFA MASTER'!$B$15:$E$3702,4,0),0) -> 0 | G42: =IFERROR(VLOOKUP(B42,'TARIFA MASTER'!$B$5:$L$4699,11,0),0) -> 0 | H42: =IFERROR(VLOOKUP(B42,'TARIFA MASTER'!$B$5:$J$3754,5,0),0) -> 0 | K42: =IFERROR(VLOOKUP(B42,'TARIFA MASTER'!$B$5:$G$3752,6,0),0) -> 0 | L42: =+G42*C42 -> 0
D43: =IFERROR(VLOOKUP(B43,'TARIFA MASTER'!$B$5:$C$3741,2,0),0) -> 0 | E43: =IFERROR(VLOOKUP(B43,'TARIFA MASTER'!B17:L3495,3,0),0) -> 0 | F43: =IFERROR(VLOOKUP(B43,'TARIFA MASTER'!$B$15:$E$3702,4,0),0) -> 0 | G43: =IFERROR(VLOOKUP(B43,'TARIFA MASTER'!$B$5:$L$4699,11,0),0) -> 0 | H43: =IFERROR(VLOOKUP(B43,'TARIFA MASTER'!$B$5:$J$3754,5,0),0) -> 0 | K43: =IFERROR(VLOOKUP(B43,'TARIFA MASTER'!$B$5:$G$3752,6,0),0) -> 0 | L43: =+G43*C43 -> 0
D44: =IFERROR(VLOOKUP(B44,'TARIFA MASTER'!$B$5:$C$3741,2,0),0) -> 0 | E44: =IFERROR(VLOOKUP(B44,'TARIFA MASTER'!B18:L3496,3,0),0) -> 0 | F44: =IFERROR(VLOOKUP(B44,'TARIFA MASTER'!$B$15:$E$3702,4,0),0) -> 0 | G44: =IFERROR(VLOOKUP(B44,'TARIFA MASTER'!$B$5:$L$4699,11,0),0) -> 0 | H44: =IFERROR(VLOOKUP(B44,'TARIFA MASTER'!$B$5:$J$3754,5,0),0) -> 0 | K44: =IFERROR(VLOOKUP(B44,'TARIFA MASTER'!$B$5:$G$3752,6,0),0) -> 0 | L44: =+G44*C44 -> 0
D45: =IFERROR(VLOOKUP(B45,'TARIFA MASTER'!$B$5:$C$3741,2,0),0) -> 0 | E45: =IFERROR(VLOOKUP(B45,'TARIFA MASTER'!B19:L3497,3,0),0) -> 0 | F45: =IFERROR(VLOOKUP(B45,'TARIFA MASTER'!$B$15:$E$3702,4,0),0) -> 0 | G45: =IFERROR(VLOOKUP(B45,'TARIFA MASTER'!$B$5:$L$4699,11,0),0) -> 0 | H45: =IFERROR(VLOOKUP(B45,'TARIFA MASTER'!$B$5:$J$3754,5,0),0) -> 0 | K45: =IFERROR(VLOOKUP(B45,'TARIFA MASTER'!$B$5:$G$3752,6,0),0) -> 0 | L45: =+G45*C45 -> 0
D46: =IFERROR(VLOOKUP(B46,'TARIFA MASTER'!$B$5:$C$3741,2,0),0) -> 0 | E46: =IFERROR(VLOOKUP(B46,'TARIFA MASTER'!B20:L3498,3,0),0) -> 0 | F46: =IFERROR(VLOOKUP(B46,'TARIFA MASTER'!$B$15:$E$3702,4,0),0) -> 0 | G46: =IFERROR(VLOOKUP(B46,'TARIFA MASTER'!$B$5:$L$4699,11,0),0) -> 0 | H46: =IFERROR(VLOOKUP(B46,'TARIFA MASTER'!$B$5:$J$3754,5,0),0) -> 0 | K46: =IFERROR(VLOOKUP(B46,'TARIFA MASTER'!$B$5:$G$3752,6,0),0) -> 0 | L46: =+G46*C46 -> 0
D47: =IFERROR(VLOOKUP(B47,'TARIFA MASTER'!$B$5:$C$3741,2,0),0) -> 0 | E47: =IFERROR(VLOOKUP(B47,'TARIFA MASTER'!B21:L3499,3,0),0) -> 0 | F47: =IFERROR(VLOOKUP(B47,'TARIFA MASTER'!$B$15:$E$3702,4,0),0) -> 0 | G47: =IFERROR(VLOOKUP(B47,'TARIFA MASTER'!$B$5:$L$4699,11,0),0) -> 0 | H47: =IFERROR(VLOOKUP(B47,'TARIFA MASTER'!$B$5:$J$3754,5,0),0) -> 0 | K47: =IFERROR(VLOOKUP(B47,'TARIFA MASTER'!$B$5:$G$3752,6,0),0) -> 0 | L47: =+G47*C47 -> 0
D48: =IFERROR(VLOOKUP(B48,'TARIFA MASTER'!$B$5:$C$3741,2,0),0) -> 0 | E48: =IFERROR(VLOOKUP(B48,'TARIFA MASTER'!B22:L3500,3,0),0) -> 0 | F48: =IFERROR(VLOOKUP(B48,'TARIFA MASTER'!$B$15:$E$3702,4,0),0) -> 0 | G48: =IFERROR(VLOOKUP(B48,'TARIFA MASTER'!$B$5:$L$4699,11,0),0) -> 0 | H48: =IFERROR(VLOOKUP(B48,'TARIFA MASTER'!$B$5:$J$3754,5,0),0) -> 0 | K48: =IFERROR(VLOOKUP(B48,'TARIFA MASTER'!$B$5:$G$3752,6,0),0) -> 0 | L48: =+G48*C48 -> 0
D49: =IFERROR(VLOOKUP(B49,'TARIFA MASTER'!$B$5:$C$3741,2,0),0) -> 0 | E49: =IFERROR(VLOOKUP(B49,'TARIFA MASTER'!B23:L3501,3,0),0) -> 0 | F49: =IFERROR(VLOOKUP(B49,'TARIFA MASTER'!$B$15:$E$3702,4,0),0) -> 0 | G49: =IFERROR(VLOOKUP(B49,'TARIFA MASTER'!$B$5:$L$4699,11,0),0) -> 0 | H49: =IFERROR(VLOOKUP(B49,'TARIFA MASTER'!$B$5:$J$3754,5,0),0) -> 0 | K49: =IFERROR(VLOOKUP(B49,'TARIFA MASTER'!$B$5:$G$3752,6,0),0) -> 0 | L49: =+G49*C49 -> 0
D50: =IFERROR(VLOOKUP(B50,'TARIFA MASTER'!$B$5:$C$3741,2,0),0) -> 0 | E50: =IFERROR(VLOOKUP(B50,'TARIFA MASTER'!B24:L3502,3,0),0) -> 0 | F50: =IFERROR(VLOOKUP(B50,'TARIFA MASTER'!$B$15:$E$3702,4,0),0) -> 0 | G50: =IFERROR(VLOOKUP(B50,'TARIFA MASTER'!$B$5:$L$4699,11,0),0) -> 0 | H50: =IFERROR(VLOOKUP(B50,'TARIFA MASTER'!$B$5:$J$3754,5,0),0) -> 0 | K50: =IFERROR(VLOOKUP(B50,'TARIFA MASTER'!$B$5:$G$3752,6,0),0) -> 0 | L50: =+G50*C50 -> 0
D51: =IFERROR(VLOOKUP(B51,'TARIFA MASTER'!$B$5:$C$3741,2,0),0) -> 0 | E51: =IFERROR(VLOOKUP(B51,'TARIFA MASTER'!B25:L3503,3,0),0) -> 0 | F51: =IFERROR(VLOOKUP(B51,'TARIFA MASTER'!$B$15:$E$3702,4,0),0) -> 0 | G51: =IFERROR(VLOOKUP(B51,'TARIFA MASTER'!$B$5:$L$4699,11,0),0) -> 0 | H51: =IFERROR(VLOOKUP(B51,'TARIFA MASTER'!$B$5:$J$3754,5,0),0) -> 0 | K51: =IFERROR(VLOOKUP(B51,'TARIFA MASTER'!$B$5:$G$3752,6,0),0) -> 0 | L51: =+G51*C51 -> 0
D52: =IFERROR(VLOOKUP(B52,'TARIFA MASTER'!$B$5:$C$3741,2,0),0) -> 0 | E52: =IFERROR(VLOOKUP(B52,'TARIFA MASTER'!B26:L3504,3,0),0) -> 0 | F52: =IFERROR(VLOOKUP(B52,'TARIFA MASTER'!$B$15:$E$3702,4,0),0) -> 0 | G52: =IFERROR(VLOOKUP(B52,'TARIFA MASTER'!$B$5:$L$4699,11,0),0) -> 0 | H52: =IFERROR(VLOOKUP(B52,'TARIFA MASTER'!$B$5:$J$3754,5,0),0) -> 0 | K52: =IFERROR(VLOOKUP(B52,'TARIFA MASTER'!$B$5:$G$3752,6,0),0) -> 0 | L52: =+G52*C52 -> 0
... D58: =IFERROR(VLOOKUP(B58,'TARIFA MASTER'!$B$5:$C$3741,2,0),0) -> 0 | E58: =IFERROR(VLOOKUP(B58,'TARIFA MASTER'!B32:L3510,3,0),0) -> 0 | F58: =IFERROR(VLOOKUP(B58,'TARIFA MASTER'!$B$15:$E$3702,4,0),0) -> 0 | G58: =IFERROR(VLOOKUP(B58,'TARIFA MASTER'!$B$5:$L$4699,11,0),0) -> 0 | H58: =IFERROR(VLOOKUP(B58,'TARIFA MASTER'!$B$5:$J$3754,5,0),0) -> 0 | K58: =IFERROR(VLOOKUP(B58,'TARIFA MASTER'!$B$5:$G$3752,6,0),0) -> 0 | L58: =+G58*C58 -> 0
D59: =IFERROR(VLOOKUP(B59,'TARIFA MASTER'!$B$5:$C$3741,2,0),0) -> 0 | E59: =IFERROR(VLOOKUP(B59,'TARIFA MASTER'!B34:L3511,3,0),0) -> 0 | F59: =IFERROR(VLOOKUP(B59,'TARIFA MASTER'!$B$15:$E$3702,4,0),0) -> 0 | G59: =IFERROR(VLOOKUP(B59,'TARIFA MASTER'!$B$5:$L$4699,11,0),0) -> 0 | H59: =IFERROR(VLOOKUP(B59,'TARIFA MASTER'!$B$5:$J$3754,5,0),0) -> 0 | K59: =IFERROR(VLOOKUP(B59,'TARIFA MASTER'!$B$5:$G$3752,6,0),0) -> 0 | L59: =+G59*C59 -> 0
D60: =IFERROR(VLOOKUP(B60,'TARIFA MASTER'!$B$5:$C$3741,2,0),0) -> 0 | E60: =IFERROR(VLOOKUP(B60,'TARIFA MASTER'!B36:L3512,3,0),0) -> 0 | F60: =IFERROR(VLOOKUP(B60,'TARIFA MASTER'!$B$15:$E$3702,4,0),0) -> 0 | G60: =IFERROR(VLOOKUP(B60,'TARIFA MASTER'!$B$5:$L$4699,11,0),0) -> 0 | H60: =IFERROR(VLOOKUP(B60,'TARIFA MASTER'!$B$5:$J$3754,5,0),0) -> 0 | K60: =IFERROR(VLOOKUP(B60,'TARIFA MASTER'!$B$5:$G$3752,6,0),0) -> 0 | L60: =+G60*C60 -> 0
D61: =IFERROR(VLOOKUP(B61,'TARIFA MASTER'!$B$5:$C$3741,2,0),0) -> 0 | E61: =IFERROR(VLOOKUP(B61,'TARIFA MASTER'!B37:L3513,3,0),0) -> 0 | F61: =IFERROR(VLOOKUP(B61,'TARIFA MASTER'!$B$15:$E$3702,4,0),0) -> 0 | G61: =IFERROR(VLOOKUP(B61,'TARIFA MASTER'!$B$5:$L$4699,11,0),0) -> 0 | H61: =IFERROR(VLOOKUP(B61,'TARIFA MASTER'!$B$5:$J$3754,5,0),0) -> 0 | K61: =IFERROR(VLOOKUP(B61,'TARIFA MASTER'!$B$5:$G$3752,6,0),0) -> 0 | L61: =+G61*C61 -> 0
D62: =IFERROR(VLOOKUP(B62,'TARIFA MASTER'!$B$5:$C$3741,2,0),0) -> 0 | E62: =IFERROR(VLOOKUP(B62,'TARIFA MASTER'!B38:L3514,3,0),0) -> 0 | F62: =IFERROR(VLOOKUP(B62,'TARIFA MASTER'!$B$15:$E$3702,4,0),0) -> 0 | G62: =IFERROR(VLOOKUP(B62,'TARIFA MASTER'!$B$5:$L$4699,11,0),0) -> 0 | H62: =IFERROR(VLOOKUP(B62,'TARIFA MASTER'!$B$5:$J$3754,5,0),0) -> 0 | K62: =IFERROR(VLOOKUP(B62,'TARIFA MASTER'!$B$5:$G$3752,6,0),0) -> 0 | L62: =+G62*C62 -> 0
D63: =IFERROR(VLOOKUP(B63,'TARIFA MASTER'!$B$5:$C$3741,2,0),0) -> 0 | E63: =IFERROR(VLOOKUP(B63,'TARIFA MASTER'!B39:L3515,3,0),0) -> 0 | F63: =IFERROR(VLOOKUP(B63,'TARIFA MASTER'!$B$15:$E$3702,4,0),0) -> 0 | G63: =IFERROR(VLOOKUP(B63,'TARIFA MASTER'!$B$5:$L$4699,11,0),0) -> 0 | H63: =IFERROR(VLOOKUP(B63,'TARIFA MASTER'!$B$5:$J$3754,5,0),0) -> 0 | K63: =IFERROR(VLOOKUP(B63,'TARIFA MASTER'!$B$5:$G$3752,6,0),0) -> 0 | L63: =+G63*C63 -> 0
D64: =IFERROR(VLOOKUP(B64,'TARIFA MASTER'!$B$5:$C$3741,2,0),0) -> 0 | E64: =IFERROR(VLOOKUP(B64,'TARIFA MASTER'!B40:L3516,3,0),0) -> 0 | F64: =IFERROR(VLOOKUP(B64,'TARIFA MASTER'!$B$15:$E$3702,4,0),0) -> 0 | G64: =IFERROR(VLOOKUP(B64,'TARIFA MASTER'!$B$5:$L$4699,11,0),0) -> 0 | H64: =IFERROR(VLOOKUP(B64,'TARIFA MASTER'!$B$5:$J$3754,5,0),0) -> 0 | K64: =IFERROR(VLOOKUP(B64,'TARIFA MASTER'!$B$5:$G$3752,6,0),0) -> 0 | L64: =+G64*C64 -> 0
D65: =IFERROR(VLOOKUP(B65,'TARIFA MASTER'!$B$5:$C$3741,2,0),0) -> 0 | E65: =IFERROR(VLOOKUP(B65,'TARIFA MASTER'!B41:L3517,3,0),0) -> 0 | F65: =IFERROR(VLOOKUP(B65,'TARIFA MASTER'!$B$15:$E$3702,4,0),0) -> 0 | G65: =IFERROR(VLOOKUP(B65,'TARIFA MASTER'!$B$5:$L$4699,11,0),0) -> 0 | H65: =IFERROR(VLOOKUP(B65,'TARIFA MASTER'!$B$5:$J$3754,5,0),0) -> 0 | K65: =IFERROR(VLOOKUP(B65,'TARIFA MASTER'!$B$5:$G$3752,6,0),0) -> 0 | L65: =+G65*C65 -> 0
D66: =IFERROR(VLOOKUP(B66,'TARIFA MASTER'!$B$5:$C$3741,2,0),0) -> 0 | E66: =IFERROR(VLOOKUP(B66,'TARIFA MASTER'!B42:L3518,3,0),0) -> 0 | F66: =IFERROR(VLOOKUP(B66,'TARIFA MASTER'!$B$15:$E$3702,4,0),0) -> 0 | G66: =IFERROR(VLOOKUP(B66,'TARIFA MASTER'!$B$5:$L$4699,11,0),0) -> 0 | H66: =IFERROR(VLOOKUP(B66,'TARIFA MASTER'!$B$5:$J$3754,5,0),0) -> 0 | K66: =IFERROR(VLOOKUP(B66,'TARIFA MASTER'!$B$5:$G$3752,6,0),0) -> 0 | L66: =+G66*C66 -> 0
D67: =IFERROR(VLOOKUP(B67,'TARIFA MASTER'!$B$5:$C$3741,2,0),0) -> 0 | E67: =IFERROR(VLOOKUP(B67,'TARIFA MASTER'!B43:L3519,3,0),0) -> 0 | F67: =IFERROR(VLOOKUP(B67,'TARIFA MASTER'!$B$15:$E$3702,4,0),0) -> 0 | G67: =IFERROR(VLOOKUP(B67,'TARIFA MASTER'!$B$5:$L$4699,11,0),0) -> 0 | H67: =IFERROR(VLOOKUP(B67,'TARIFA MASTER'!$B$5:$J$3754,5,0),0) -> 0 | K67: =IFERROR(VLOOKUP(B67,'TARIFA MASTER'!$B$5:$G$3752,6,0),0) -> 0 | L67: =+G67*C67 -> 0
D68: =IFERROR(VLOOKUP(B68,'TARIFA MASTER'!$B$5:$C$3741,2,0),0) -> 0 | E68: =IFERROR(VLOOKUP(B68,'TARIFA MASTER'!B44:L3520,3,0),0) -> 0 | F68: =IFERROR(VLOOKUP(B68,'TARIFA MASTER'!$B$15:$E$3702,4,0),0) -> 0 | G68: =IFERROR(VLOOKUP(B68,'TARIFA MASTER'!$B$5:$L$4699,11,0),0) -> 0 | H68: =IFERROR(VLOOKUP(B68,'TARIFA MASTER'!$B$5:$J$3754,5,0),0) -> 0 | K68: =IFERROR(VLOOKUP(B68,'TARIFA MASTER'!$B$5:$G$3752,6,0),0) -> 0 | L68: =+G68*C68 -> 0
D69: =IFERROR(VLOOKUP(B69,'TARIFA MASTER'!$B$5:$C$3741,2,0),0) -> 0 | E69: =IFERROR(VLOOKUP(B69,'TARIFA MASTER'!B45:L3521,3,0),0) -> 0 | F69: =IFERROR(VLOOKUP(B69,'TARIFA MASTER'!$B$15:$E$3702,4,0),0) -> 0 | G69: =IFERROR(VLOOKUP(B69,'TARIFA MASTER'!$B$5:$L$4699,11,0),0) -> 0 | H69: =IFERROR(VLOOKUP(B69,'TARIFA MASTER'!$B$5:$J$3754,5,0),0) -> 0 | K69: =IFERROR(VLOOKUP(B69,'TARIFA MASTER'!$B$5:$G$3752,6,0),0) -> 0 | L69: =+G69*C69 -> 0
D70: =IFERROR(VLOOKUP(B70,'TARIFA MASTER'!$B$5:$C$3741,2,0),0) -> 0 | E70: =IFERROR(VLOOKUP(B70,'TARIFA MASTER'!B13:L3472,3,0),0) -> 0 | F70: =IFERROR(VLOOKUP(B70,'TARIFA MASTER'!$B$15:$E$3702,4,0),0) -> 0 | G70: =IFERROR(VLOOKUP(B70,'TARIFA MASTER'!$B$5:$L$4699,11,0),0) -> 0 | H70: =IFERROR(VLOOKUP(B70,'TARIFA MASTER'!$B$5:$J$3754,5,0),0) -> 0 | K70: =IFERROR(VLOOKUP(B70,'TARIFA MASTER'!$B$5:$G$3752,6,0),0) -> 0 | L70: =+G70*C70 -> 0
D71: =IFERROR(VLOOKUP(B71,'TARIFA MASTER'!$B$5:$C$3741,2,0),0) -> 0 | E71: =IFERROR(VLOOKUP(B71,'TARIFA MASTER'!B13:L3473,3,0),0) -> 0 | F71: =IFERROR(VLOOKUP(B71,'TARIFA MASTER'!$B$15:$E$3702,4,0),0) -> 0 | G71: =IFERROR(VLOOKUP(B71,'TARIFA MASTER'!$B$5:$L$4699,11,0),0) -> 0 | H71: =IFERROR(VLOOKUP(B71,'TARIFA MASTER'!$B$5:$J$3754,5,0),0) -> 0 | K71: =IFERROR(VLOOKUP(B71,'TARIFA MASTER'!$B$5:$G$3752,6,0),0) -> 0 | L71: =+G71*C71 -> 0
D72: =IFERROR(VLOOKUP(B72,'TARIFA MASTER'!$B$5:$C$3741,2,0),0) -> 0 | E72: =IFERROR(VLOOKUP(B72,'TARIFA MASTER'!B13:L3474,3,0),0) -> 0 | F72: =IFERROR(VLOOKUP(B72,'TARIFA MASTER'!$B$15:$E$3702,4,0),0) -> 0 | G72: =IFERROR(VLOOKUP(B72,'TARIFA MASTER'!$B$5:$L$4699,11,0),0) -> 0 | H72: =IFERROR(VLOOKUP(B72,'TARIFA MASTER'!$B$5:$J$3754,5,0),0) -> 0 | K72: =IFERROR(VLOOKUP(B72,'TARIFA MASTER'!$B$5:$G$3752,6,0),0) -> 0 | L72: =+G72*C72 -> 0
D73: =IFERROR(VLOOKUP(B73,'TARIFA MASTER'!$B$5:$C$3741,2,0),0) -> 0 | E73: =IFERROR(VLOOKUP(B73,'TARIFA MASTER'!B13:L3475,3,0),0) -> 0 | F73: =IFERROR(VLOOKUP(B73,'TARIFA MASTER'!$B$15:$E$3702,4,0),0) -> 0 | G73: =IFERROR(VLOOKUP(B73,'TARIFA MASTER'!$B$5:$L$4699,11,0),0) -> 0 | H73: =IFERROR(VLOOKUP(B73,'TARIFA MASTER'!$B$5:$J$3754,5,0),0) -> 0 | K73: =IFERROR(VLOOKUP(B73,'TARIFA MASTER'!$B$5:$G$3752,6,0),0) -> 0 | L73: =+G73*C73 -> 0
D74: =IFERROR(VLOOKUP(B74,'TARIFA MASTER'!$B$5:$C$3741,2,0),0) -> 0 | E74: =IFERROR(VLOOKUP(B74,'TARIFA MASTER'!B13:L3476,3,0),0) -> 0 | F74: =IFERROR(VLOOKUP(B74,'TARIFA MASTER'!$B$15:$E$3702,4,0),0) -> 0 | G74: =IFERROR(VLOOKUP(B74,'TARIFA MASTER'!$B$5:$L$4699,11,0),0) -> 0 | H74: =IFERROR(VLOOKUP(B74,'TARIFA MASTER'!$B$5:$J$3754,5,0),0) -> 0 | K74: =IFERROR(VLOOKUP(B74,'TARIFA MASTER'!$B$5:$G$3752,6,0),0) -> 0 | L74: =+G74*C74 -> 0
D75: =IFERROR(VLOOKUP(B75,'TARIFA MASTER'!$B$5:$C$3741,2,0),0) -> 0 | E75: =IFERROR(VLOOKUP(B75,'TARIFA MASTER'!B13:L3477,3,0),0) -> 0 | F75: =IFERROR(VLOOKUP(B75,'TARIFA MASTER'!$B$15:$E$3702,4,0),0) -> 0 | G75: =IFERROR(VLOOKUP(B75,'TARIFA MASTER'!$B$5:$L$4699,11,0),0) -> 0 | H75: =IFERROR(VLOOKUP(B75,'TARIFA MASTER'!$B$5:$J$3754,5,0),0) -> 0 | K75: =IFERROR(VLOOKUP(B75,'TARIFA MASTER'!$B$5:$G$3752,6,0),0) -> 0 | L75: =+G75*C75 -> 0
D76: =IFERROR(VLOOKUP(B76,'TARIFA MASTER'!$B$5:$C$3741,2,0),0) -> 0 | E76: =IFERROR(VLOOKUP(B76,'TARIFA MASTER'!B13:L3477,3,0),0) -> 0 | F76: =IFERROR(VLOOKUP(B76,'TARIFA MASTER'!$B$15:$E$3702,4,0),0) -> 0 | G76: =IFERROR(VLOOKUP(B76,'TARIFA MASTER'!$B$5:$L$4699,11,0),0) -> 0 | H76: =IFERROR(VLOOKUP(B76,'TARIFA MASTER'!$B$5:$J$3754,5,0),0) -> 0 | K76: =IFERROR(VLOOKUP(B76,'TARIFA MASTER'!$B$5:$G$3752,6,0),0) -> 0 | L76: =+G76*C76 -> 0
D77: =IFERROR(VLOOKUP(B77,'TARIFA MASTER'!$B$5:$C$3741,2,0),0) -> 0 | E77: =IFERROR(VLOOKUP(B77,'TARIFA MASTER'!B13:L3478,3,0),0) -> 0 | F77: =IFERROR(VLOOKUP(B77,'TARIFA MASTER'!$B$15:$E$3702,4,0),0) -> 0 | G77: =IFERROR(VLOOKUP(B77,'TARIFA MASTER'!$B$5:$L$4699,11,0),0) -> 0 | H77: =IFERROR(VLOOKUP(B77,'TARIFA MASTER'!$B$5:$J$3754,5,0),0) -> 0 | K77: =IFERROR(VLOOKUP(B77,'TARIFA MASTER'!$B$5:$G$3752,6,0),0) -> 0 | L77: =+G77*C77 -> 0
D78: =IFERROR(VLOOKUP(B78,'TARIFA MASTER'!$B$5:$C$3741,2,0),0) -> 0 | E78: =IFERROR(VLOOKUP(B78,'TARIFA MASTER'!B13:L3479,3,0),0) -> 0 | F78: =IFERROR(VLOOKUP(B78,'TARIFA MASTER'!$B$15:$E$3702,4,0),0) -> 0 | G78: =IFERROR(VLOOKUP(B78,'TARIFA MASTER'!$B$5:$L$4699,11,0),0) -> 0 | H78: =IFERROR(VLOOKUP(B78,'TARIFA MASTER'!$B$5:$J$3754,5,0),0) -> 0 | K78: =IFERROR(VLOOKUP(B78,'TARIFA MASTER'!$B$5:$G$3752,6,0),0) -> 0 | L78: =+G78*C78 -> 0
D79: =IFERROR(VLOOKUP(B79,'TARIFA MASTER'!$B$5:$C$3741,2,0),0) -> 0 | E79: =IFERROR(VLOOKUP(B79,'TARIFA MASTER'!B13:L3479,3,0),0) -> 0 | F79: =IFERROR(VLOOKUP(B79,'TARIFA MASTER'!$B$15:$E$3702,4,0),0) -> 0 | G79: =IFERROR(VLOOKUP(B79,'TARIFA MASTER'!$B$5:$L$4699,11,0),0) -> 0 | H79: =IFERROR(VLOOKUP(B79,'TARIFA MASTER'!$B$5:$J$3754,5,0),0) -> 0 | K79: =IFERROR(VLOOKUP(B79,'TARIFA MASTER'!$B$5:$G$3752,6,0),0) -> 0 | L79: =+G79*C79 -> 0
D80: =IFERROR(VLOOKUP(B80,'TARIFA MASTER'!$B$5:$C$3741,2,0),0) -> 0 | E80: =IFERROR(VLOOKUP(B80,'TARIFA MASTER'!B13:L3480,3,0),0) -> 0 | F80: =IFERROR(VLOOKUP(B80,'TARIFA MASTER'!$B$15:$E$3702,4,0),0) -> 0 | G80: =IFERROR(VLOOKUP(B80,'TARIFA MASTER'!$B$5:$L$4699,11,0),0) -> 0 | H80: =IFERROR(VLOOKUP(B80,'TARIFA MASTER'!$B$5:$J$3754,5,0),0) -> 0 | K80: =IFERROR(VLOOKUP(B80,'TARIFA MASTER'!$B$5:$G$3752,6,0),0) -> 0 | L80: =+G80*C80 -> 0
D81: =IFERROR(VLOOKUP(B81,'TARIFA MASTER'!$B$5:$C$3741,2,0),0) -> 0 | E81: =IFERROR(VLOOKUP(B81,'TARIFA MASTER'!B13:L3481,3,0),0) -> 0 | F81: =IFERROR(VLOOKUP(B81,'TARIFA MASTER'!$B$15:$E$3702,4,0),0) -> 0 | G81: =IFERROR(VLOOKUP(B81,'TARIFA MASTER'!$B$5:$L$4699,11,0),0) -> 0 | H81: =IFERROR(VLOOKUP(B81,'TARIFA MASTER'!$B$5:$J$3754,5,0),0) -> 0 | K81: =IFERROR(VLOOKUP(B81,'TARIFA MASTER'!$B$5:$G$3752,6,0),0) -> 0 | L81: =+G81*C81 -> 0
D82: =IFERROR(VLOOKUP(B82,'TARIFA MASTER'!$B$5:$C$3741,2,0),0) -> 0 | E82: =IFERROR(VLOOKUP(B82,'TARIFA MASTER'!B13:L3482,3,0),0) -> 0 | F82: =IFERROR(VLOOKUP(B82,'TARIFA MASTER'!$B$15:$E$3702,4,0),0) -> 0 | G82: =IFERROR(VLOOKUP(B82,'TARIFA MASTER'!$B$5:$L$4699,11,0),0) -> 0 | H82: =IFERROR(VLOOKUP(B82,'TARIFA MASTER'!$B$5:$J$3754,5,0),0) -> 0 | K82: =IFERROR(VLOOKUP(B82,'TARIFA MASTER'!$B$5:$G$3752,6,0),0) -> 0 | L82: =+G82*C82 -> 0
D83: =IFERROR(VLOOKUP(B83,'TARIFA MASTER'!$B$5:$C$3741,2,0),0) -> 0 | E83: =IFERROR(VLOOKUP(B83,'TARIFA MASTER'!B13:L3483,3,0),0) -> 0 | F83: =IFERROR(VLOOKUP(B83,'TARIFA MASTER'!$B$15:$E$3702,4,0),0) -> 0 | G83: =IFERROR(VLOOKUP(B83,'TARIFA MASTER'!$B$5:$L$4699,11,0),0) -> 0 | H83: =IFERROR(VLOOKUP(B83,'TARIFA MASTER'!$B$5:$J$3754,5,0),0) -> 0 | K83: =IFERROR(VLOOKUP(B83,'TARIFA MASTER'!$B$5:$G$3752,6,0),0) -> 0 | L83: =+G83*C83 -> 0
D84: =IFERROR(VLOOKUP(B84,'TARIFA MASTER'!$B$5:$C$3741,2,0),0) -> 0 | E84: =IFERROR(VLOOKUP(B84,'TARIFA MASTER'!B13:L3484,3,0),0) -> 0 | F84: =IFERROR(VLOOKUP(B84,'TARIFA MASTER'!$B$15:$E$3702,4,0),0) -> 0 | G84: =IFERROR(VLOOKUP(B84,'TARIFA MASTER'!$B$5:$L$4699,11,0),0) -> 0 | H84: =IFERROR(VLOOKUP(B84,'TARIFA MASTER'!$B$5:$J$3754,5,0),0) -> 0 | K84: =IFERROR(VLOOKUP(B84,'TARIFA MASTER'!$B$5:$G$3752,6,0),0) -> 0 | L84: =+G84*C84 -> 0
D85: =IFERROR(VLOOKUP(B85,'TARIFA MASTER'!$B$5:$C$3741,2,0),0) -> 0 | E85: =IFERROR(VLOOKUP(B85,'TARIFA MASTER'!B13:L3472,3,0),0) -> 0 | F85: =IFERROR(VLOOKUP(B85,'TARIFA MASTER'!$B$15:$E$3702,4,0),0) -> 0 | G85: =IFERROR(VLOOKUP(B85,'TARIFA MASTER'!$B$5:$L$4699,11,0),0) -> 0 | H85: =IFERROR(VLOOKUP(B85,'TARIFA MASTER'!$B$5:$J$3754,5,0),0) -> 0 | K85: =IFERROR(VLOOKUP(B85,'TARIFA MASTER'!$B$5:$G$3752,6,0),0) -> 0 | L85: =+G85*C85 -> 0 | M85: =IFERROR(VLOOKUP(B85,[2]PESOS!A$2:D$3072,4,0),0) -> 0 | N85: =+M85*C85 -> 0
D86: =IFERROR(VLOOKUP(B86,'TARIFA MASTER'!$B$5:$C$3741,2,0),0) -> 0 | E86: =IFERROR(VLOOKUP(B86,'TARIFA MASTER'!B13:L3473,3,0),0) -> 0 | F86: =IFERROR(VLOOKUP(B86,'TARIFA MASTER'!$B$15:$E$3702,4,0),0) -> 0 | G86: =IFERROR(VLOOKUP(B86,'TARIFA MASTER'!$B$5:$L$4699,11,0),0) -> 0 | H86: =IFERROR(VLOOKUP(B86,'TARIFA MASTER'!$B$5:$J$3754,5,0),0) -> 0 | K86: =IFERROR(VLOOKUP(B86,'TARIFA MASTER'!$B$5:$G$3752,6,0),0) -> 0 | L86: =+G86*C86 -> 0 | M86: =IFERROR(VLOOKUP(B86,[2]PESOS!A$2:D$3072,4,0),0) -> 0 | N86: =+M86*C86 -> 0
D87: =IFERROR(VLOOKUP(B87,'TARIFA MASTER'!$B$5:$C$3741,2,0),0) -> 0 | E87: =IFERROR(VLOOKUP(B87,'TARIFA MASTER'!B13:L3474,3,0),0) -> 0 | F87: =IFERROR(VLOOKUP(B87,'TARIFA MASTER'!$B$15:$E$3702,4,0),0) -> 0 | G87: =IFERROR(VLOOKUP(B87,'TARIFA MASTER'!$B$5:$L$4699,11,0),0) -> 0 | H87: =IFERROR(VLOOKUP(B87,'TARIFA MASTER'!$B$5:$J$3754,5,0),0) -> 0 | K87: =IFERROR(VLOOKUP(B87,'TARIFA MASTER'!$B$5:$G$3752,6,0),0) -> 0 | L87: =+G87*C87 -> 0 | M87: =IFERROR(VLOOKUP(B87,[2]PESOS!A$2:D$3072,4,0),0) -> 0 | N87: =+M87*C87 -> 0
D88: =IFERROR(VLOOKUP(B88,'TARIFA MASTER'!$B$5:$C$3741,2,0),0) -> 0 | E88: =IFERROR(VLOOKUP(B88,'TARIFA MASTER'!B13:L3475,3,0),0) -> 0 | F88: =IFERROR(VLOOKUP(B88,'TARIFA MASTER'!$B$15:$E$3702,4,0),0) -> 0 | G88: =IFERROR(VLOOKUP(B88,'TARIFA MASTER'!$B$5:$L$4699,11,0),0) -> 0 | H88: =IFERROR(VLOOKUP(B88,'TARIFA MASTER'!$B$5:$J$3754,5,0),0) -> 0 | K88: =IFERROR(VLOOKUP(B88,'TARIFA MASTER'!$B$5:$G$3752,6,0),0) -> 0 | L88: =+G88*C88 -> 0 | M88: =IFERROR(VLOOKUP(B88,[2]PESOS!A$2:D$3072,4,0),0) -> 0 | N88: =+M88*C88 -> 0
D89: =IFERROR(VLOOKUP(B89,'TARIFA MASTER'!$B$5:$C$3741,2,0),0) -> 0 | E89: =IFERROR(VLOOKUP(B89,'TARIFA MASTER'!B13:L3476,3,0),0) -> 0 | F89: =IFERROR(VLOOKUP(B89,'TARIFA MASTER'!$B$15:$E$3702,4,0),0) -> 0 | G89: =IFERROR(VLOOKUP(B89,'TARIFA MASTER'!$B$5:$L$4699,11,0),0) -> 0 | H89: =IFERROR(VLOOKUP(B89,'TARIFA MASTER'!$B$5:$J$3754,5,0),0) -> 0 | K89: =IFERROR(VLOOKUP(B89,'TARIFA MASTER'!$B$5:$G$3752,6,0),0) -> 0 | L89: =+G89*C89 -> 0 | M89: =IFERROR(VLOOKUP(B89,[2]PESOS!A$2:D$3072,4,0),0) -> 0 | N89: =+M89*C89 -> 0
D90: =IFERROR(VLOOKUP(B90,'TARIFA MASTER'!$B$5:$C$3741,2,0),0) -> 0 | E90: =IFERROR(VLOOKUP(B90,'TARIFA MASTER'!B13:L3477,3,0),0) -> 0 | F90: =IFERROR(VLOOKUP(B90,'TARIFA MASTER'!$B$15:$E$3702,4,0),0) -> 0 | G90: =IFERROR(VLOOKUP(B90,'TARIFA MASTER'!$B$5:$L$4699,11,0),0) -> 0 | H90: =IFERROR(VLOOKUP(B90,'TARIFA MASTER'!$B$5:$J$3754,5,0),0) -> 0 | K90: =IFERROR(VLOOKUP(B90,'TARIFA MASTER'!$B$5:$G$3752,6,0),0) -> 0 | L90: =+G90*C90 -> 0 | M90: =IFERROR(VLOOKUP(B90,[2]PESOS!A$2:D$3072,4,0),0) -> 0 | N90: =+M90*C90 -> 0
D91: =IFERROR(VLOOKUP(B91,'TARIFA MASTER'!$B$5:$C$3741,2,0),0) -> 0 | E91: =IFERROR(VLOOKUP(B91,'TARIFA MASTER'!B13:L3477,3,0),0) -> 0 | F91: =IFERROR(VLOOKUP(B91,'TARIFA MASTER'!$B$15:$E$3702,4,0),0) -> 0 | G91: =IFERROR(VLOOKUP(B91,'TARIFA MASTER'!$B$5:$L$4699,11,0),0) -> 0 | H91: =IFERROR(VLOOKUP(B91,'TARIFA MASTER'!$B$5:$J$3754,5,0),0) -> 0 | K91: =IFERROR(VLOOKUP(B91,'TARIFA MASTER'!$B$5:$G$3752,6,0),0) -> 0 | L91: =+G91*C91 -> 0 | M91: =IFERROR(VLOOKUP(B91,[2]PESOS!A$2:D$3072,4,0),0) -> 0 | N91: =+M91*C91 -> 0
D92: =IFERROR(VLOOKUP(B92,'TARIFA MASTER'!$B$5:$C$3741,2,0),0) -> 0 | E92: =IFERROR(VLOOKUP(B92,'TARIFA MASTER'!B13:L3478,3,0),0) -> 0 | F92: =IFERROR(VLOOKUP(B92,'TARIFA MASTER'!$B$15:$E$3702,4,0),0) -> 0 | G92: =IFERROR(VLOOKUP(B92,'TARIFA MASTER'!$B$5:$L$4699,11,0),0) -> 0 | H92: =IFERROR(VLOOKUP(B92,'TARIFA MASTER'!$B$5:$J$3754,5,0),0) -> 0 | K92: =IFERROR(VLOOKUP(B92,'TARIFA MASTER'!$B$5:$G$3752,6,0),0) -> 0 | L92: =+G92*C92 -> 0 | M92: =IFERROR(VLOOKUP(B92,[2]PESOS!A$2:D$3072,4,0),0) -> 0 | N92: =+M92*C92 -> 0
D93: =IFERROR(VLOOKUP(B93,'TARIFA MASTER'!$B$5:$C$3741,2,0),0) -> 0 | E93: =IFERROR(VLOOKUP(B93,'TARIFA MASTER'!B13:L3479,3,0),0) -> 0 | F93: =IFERROR(VLOOKUP(B93,'TARIFA MASTER'!$B$15:$E$3702,4,0),0) -> 0 | G93: =IFERROR(VLOOKUP(B93,'TARIFA MASTER'!$B$5:$L$4699,11,0),0) -> 0 | H93: =IFERROR(VLOOKUP(B93,'TARIFA MASTER'!$B$5:$J$3754,5,0),0) -> 0 | K93: =IFERROR(VLOOKUP(B93,'TARIFA MASTER'!$B$5:$G$3752,6,0),0) -> 0 | L93: =+G93*C93 -> 0 | M93: =IFERROR(VLOOKUP(B93,[2]PESOS!A$2:D$3072,4,0),0) -> 0 | N93: =+M93*C93 -> 0
D94: =IFERROR(VLOOKUP(B94,'TARIFA MASTER'!$B$5:$C$3741,2,0),0) -> 0 | E94: =IFERROR(VLOOKUP(B94,'TARIFA MASTER'!B13:L3479,3,0),0) -> 0 | F94: =IFERROR(VLOOKUP(B94,'TARIFA MASTER'!$B$15:$E$3702,4,0),0) -> 0 | G94: =IFERROR(VLOOKUP(B94,'TARIFA MASTER'!$B$5:$L$4699,11,0),0) -> 0 | H94: =IFERROR(VLOOKUP(B94,'TARIFA MASTER'!$B$5:$J$3754,5,0),0) -> 0 | K94: =IFERROR(VLOOKUP(B94,'TARIFA MASTER'!$B$5:$G$3752,6,0),0) -> 0 | L94: =+G94*C94 -> 0 | M94: =IFERROR(VLOOKUP(B94,[2]PESOS!A$2:D$3072,4,0),0) -> 0 | N94: =+M94*C94 -> 0
D95: =IFERROR(VLOOKUP(B95,'TARIFA MASTER'!$B$5:$C$3741,2,0),0) -> 0 | E95: =IFERROR(VLOOKUP(B95,'TARIFA MASTER'!B13:L3480,3,0),0) -> 0 | F95: =IFERROR(VLOOKUP(B95,'TARIFA MASTER'!$B$15:$E$3702,4,0),0) -> 0 | G95: =IFERROR(VLOOKUP(B95,'TARIFA MASTER'!$B$5:$L$4699,11,0),0) -> 0 | H95: =IFERROR(VLOOKUP(B95,'TARIFA MASTER'!$B$5:$J$3754,5,0),0) -> 0 | K95: =IFERROR(VLOOKUP(B95,'TARIFA MASTER'!$B$5:$G$3752,6,0),0) -> 0 | L95: =+G95*C95 -> 0 | M95: =IFERROR(VLOOKUP(B95,[2]PESOS!A$2:D$3072,4,0),0) -> 0 | N95: =+M95*C95 -> 0
D96: =IFERROR(VLOOKUP(B96,'TARIFA MASTER'!$B$5:$C$3741,2,0),0) -> 0 | E96: =IFERROR(VLOOKUP(B96,'TARIFA MASTER'!B13:L3481,3,0),0) -> 0 | F96: =IFERROR(VLOOKUP(B96,'TARIFA MASTER'!$B$15:$E$3702,4,0),0) -> 0 | G96: =IFERROR(VLOOKUP(B96,'TARIFA MASTER'!$B$5:$L$4699,11,0),0) -> 0 | H96: =IFERROR(VLOOKUP(B96,'TARIFA MASTER'!$B$5:$J$3754,5,0),0) -> 0 | K96: =IFERROR(VLOOKUP(B96,'TARIFA MASTER'!$B$5:$G$3752,6,0),0) -> 0 | L96: =+G96*C96 -> 0 | M96: =IFERROR(VLOOKUP(B96,[2]PESOS!A$2:D$3072,4,0),0) -> 0 | N96: =+M96*C96 -> 0
D97: =IFERROR(VLOOKUP(B97,'TARIFA MASTER'!$B$5:$C$3741,2,0),0) -> 0 | E97: =IFERROR(VLOOKUP(B97,'TARIFA MASTER'!B13:L3482,3,0),0) -> 0 | F97: =IFERROR(VLOOKUP(B97,'TARIFA MASTER'!$B$15:$E$3702,4,0),0) -> 0 | G97: =IFERROR(VLOOKUP(B97,'TARIFA MASTER'!$B$5:$L$4699,11,0),0) -> 0 | H97: =IFERROR(VLOOKUP(B97,'TARIFA MASTER'!$B$5:$J$3754,5,0),0) -> 0 | K97: =IFERROR(VLOOKUP(B97,'TARIFA MASTER'!$B$5:$G$3752,6,0),0) -> 0 | L97: =+G97*C97 -> 0 | M97: =IFERROR(VLOOKUP(B97,[2]PESOS!A$2:D$3072,4,0),0) -> 0 | N97: =+M97*C97 -> 0
D98: =IFERROR(VLOOKUP(B98,'TARIFA MASTER'!$B$5:$C$3741,2,0),0) -> 0 | E98: =IFERROR(VLOOKUP(B98,'TARIFA MASTER'!B13:L3483,3,0),0) -> 0 | F98: =IFERROR(VLOOKUP(B98,'TARIFA MASTER'!$B$15:$E$3702,4,0),0) -> 0 | G98: =IFERROR(VLOOKUP(B98,'TARIFA MASTER'!$B$5:$L$4699,11,0),0) -> 0 | H98: =IFERROR(VLOOKUP(B98,'TARIFA MASTER'!$B$5:$J$3754,5,0),0) -> 0 | K98: =IFERROR(VLOOKUP(B98,'TARIFA MASTER'!$B$5:$G$3752,6,0),0) -> 0 | L98: =+G98*C98 -> 0 | M98: =IFERROR(VLOOKUP(B98,[2]PESOS!A$2:D$3072,4,0),0) -> 0 | N98: =+M98*C98 -> 0
D99: =IFERROR(VLOOKUP(B99,'TARIFA MASTER'!$B$5:$C$3741,2,0),0) -> 0 | E99: =IFERROR(VLOOKUP(B99,'TARIFA MASTER'!B13:L3484,3,0),0) -> 0 | F99: =IFERROR(VLOOKUP(B99,'TARIFA MASTER'!$B$15:$E$3702,4,0),0) -> 0 | G99: =IFERROR(VLOOKUP(B99,'TARIFA MASTER'!$B$5:$L$4699,11,0),0) -> 0 | H99: =IFERROR(VLOOKUP(B99,'TARIFA MASTER'!$B$5:$J$3754,5,0),0) -> 0 | K99: =IFERROR(VLOOKUP(B99,'TARIFA MASTER'!$B$5:$G$3752,6,0),0) -> 0 | L99: =+G99*C99 -> 0 | M99: =IFERROR(VLOOKUP(B99,[2]PESOS!A$2:D$3072,4,0),0) -> 0 | N99: =+M99*C99 -> 0
D100: =IFERROR(VLOOKUP(B100,'TARIFA MASTER'!$B$5:$C$3741,2,0),0) -> 0 | E100: =IFERROR(VLOOKUP(B100,'TARIFA MASTER'!B13:L3485,3,0),0) -> 0 | F100: =IFERROR(VLOOKUP(B100,'TARIFA MASTER'!$B$15:$E$3702,4,0),0) -> 0 | G100: =IFERROR(VLOOKUP(B100,'TARIFA MASTER'!$B$5:$L$4699,11,0),0) -> 0 | H100: =IFERROR(VLOOKUP(B100,'TARIFA MASTER'!$B$5:$J$3754,5,0),0) -> 0 | K100: =IFERROR(VLOOKUP(B100,'TARIFA MASTER'!$B$5:$G$3752,6,0),0) -> 0 | L100: =+G100*C100 -> 0 | M100: =IFERROR(VLOOKUP(B100,[2]PESOS!A$2:D$3072,4,0),0) -> 0 | N100: =+M100*C100 -> 0
D101: =IFERROR(VLOOKUP(B101,'TARIFA MASTER'!$B$5:$C$3741,2,0),0) -> 0 | E101: =IFERROR(VLOOKUP(B101,'TARIFA MASTER'!B13:L3486,3,0),0) -> 0 | F101: =IFERROR(VLOOKUP(B101,'TARIFA MASTER'!$B$15:$E$3702,4,0),0) -> 0 | G101: =IFERROR(VLOOKUP(B101,'TARIFA MASTER'!$B$5:$L$4699,11,0),0) -> 0 | H101: =IFERROR(VLOOKUP(B101,'TARIFA MASTER'!$B$5:$J$3754,5,0),0) -> 0 | K101: =IFERROR(VLOOKUP(B101,'TARIFA MASTER'!$B$5:$G$3752,6,0),0) -> 0 | L101: =+G101*C101 -> 0 | M101: =IFERROR(VLOOKUP(B101,[2]PESOS!A$2:D$3072,4,0),0) -> 0 | N101: =+M101*C101 -> 0
D102: =IFERROR(VLOOKUP(B102,'TARIFA MASTER'!$B$5:$C$3741,2,0),0) -> 0 | E102: =IFERROR(VLOOKUP(B102,'TARIFA MASTER'!B13:L3487,3,0),0) -> 0 | F102: =IFERROR(VLOOKUP(B102,'TARIFA MASTER'!$B$15:$E$3702,4,0),0) -> 0 | G102: =IFERROR(VLOOKUP(B102,'TARIFA MASTER'!$B$5:$L$4699,11,0),0) -> 0 | H102: =IFERROR(VLOOKUP(B102,'TARIFA MASTER'!$B$5:$J$3754,5,0),0) -> 0 | K102: =IFERROR(VLOOKUP(B102,'TARIFA MASTER'!$B$5:$G$3752,6,0),0) -> 0 | L102: =+G102*C102 -> 0 | M102: =IFERROR(VLOOKUP(B102,[2]PESOS!A$2:D$3072,4,0),0) -> 0 | N102: =+M102*C102 -> 0
D103: =IFERROR(VLOOKUP(B103,'TARIFA MASTER'!$B$5:$C$3741,2,0),0) -> 0 | E103: =IFERROR(VLOOKUP(B103,'TARIFA MASTER'!B13:L3488,3,0),0) -> 0 | F103: =IFERROR(VLOOKUP(B103,'TARIFA MASTER'!$B$15:$E$3702,4,0),0) -> 0 | G103: =IFERROR(VLOOKUP(B103,'TARIFA MASTER'!$B$5:$L$4699,11,0),0) -> 0 | H103: =IFERROR(VLOOKUP(B103,'TARIFA MASTER'!$B$5:$J$3754,5,0),0) -> 0 | K103: =IFERROR(VLOOKUP(B103,'TARIFA MASTER'!$B$5:$G$3752,6,0),0) -> 0 | L103: =+G103*C103 -> 0 | M103: =IFERROR(VLOOKUP(B103,[2]PESOS!A$2:D$3072,4,0),0) -> 0 | N103: =+M103*C103 -> 0
D104: =IFERROR(VLOOKUP(B104,'TARIFA MASTER'!$B$5:$C$3741,2,0),0) -> 0 | E104: =IFERROR(VLOOKUP(B104,'TARIFA MASTER'!B13:L3489,3,0),0) -> 0 | F104: =IFERROR(VLOOKUP(B104,'TARIFA MASTER'!$B$15:$E$3702,4,0),0) -> 0 | G104: =IFERROR(VLOOKUP(B104,'TARIFA MASTER'!$B$5:$L$4699,11,0),0) -> 0 | H104: =IFERROR(VLOOKUP(B104,'TARIFA MASTER'!$B$5:$J$3754,5,0),0) -> 0 | K104: =IFERROR(VLOOKUP(B104,'TARIFA MASTER'!$B$5:$G$3752,6,0),0) -> 0 | L104: =+G104*C104 -> 0 | M104: =IFERROR(VLOOKUP(B104,[2]PESOS!A$2:D$3072,4,0),0) -> 0 | N104: =+M104*C104 -> 0
D105: =IFERROR(VLOOKUP(B105,'TARIFA MASTER'!$B$5:$C$3741,2,0),0) -> 0 | E105: =IFERROR(VLOOKUP(B105,'TARIFA MASTER'!B13:L3490,3,0),0) -> 0 | F105: =IFERROR(VLOOKUP(B105,'TARIFA MASTER'!$B$15:$E$3702,4,0),0) -> 0 | G105: =IFERROR(VLOOKUP(B105,'TARIFA MASTER'!$B$5:$L$4699,11,0),0) -> 0 | H105: =IFERROR(VLOOKUP(B105,'TARIFA MASTER'!$B$5:$J$3754,5,0),0) -> 0 | K105: =IFERROR(VLOOKUP(B105,'TARIFA MASTER'!$B$5:$G$3752,6,0),0) -> 0 | L105: =+G105*C105 -> 0 | M105: =IFERROR(VLOOKUP(B105,[2]PESOS!A$2:D$3072,4,0),0) -> 0 | N105: =+M105*C105 -> 0
D106: =IFERROR(VLOOKUP(B106,'TARIFA MASTER'!$B$5:$C$3741,2,0),0) -> 0 | E106: =IFERROR(VLOOKUP(B106,'TARIFA MASTER'!B13:L3511,3,0),0) -> 0 | F106: =IFERROR(VLOOKUP(B106,'TARIFA MASTER'!$B$15:$E$3702,4,0),0) -> 0 | G106: =IFERROR(VLOOKUP(B106,'TARIFA MASTER'!$B$5:$L$4699,11,0),0) -> 0 | H106: =IFERROR(VLOOKUP(B106,'TARIFA MASTER'!$B$5:$J$3754,5,0),0) -> 0 | K106: =IFERROR(VLOOKUP(B106,'TARIFA MASTER'!$B$5:$G$3752,6,0),0) -> 0 | L106: =+G106*C106 -> 0 | M106: =IFERROR(VLOOKUP(B106,[2]PESOS!A$2:D$3072,4,0),0) -> 0 | N106: =+M106*C106 -> 0
D107: =IFERROR(VLOOKUP(B107,'TARIFA MASTER'!$B$5:$C$3741,2,0),0) -> 0 | E107: =IFERROR(VLOOKUP(B107,'TARIFA MASTER'!B13:L3512,3,0),0) -> 0 | F107: =IFERROR(VLOOKUP(B107,'TARIFA MASTER'!$B$15:$E$3702,4,0),0) -> 0 | G107: =IFERROR(VLOOKUP(B107,'TARIFA MASTER'!$B$5:$L$4699,11,0),0) -> 0 | H107: =IFERROR(VLOOKUP(B107,'TARIFA MASTER'!$B$5:$J$3754,5,0),0) -> 0 | K107: =IFERROR(VLOOKUP(B107,'TARIFA MASTER'!$B$5:$G$3752,6,0),0) -> 0 | L107: =+G107*C107 -> 0 | M107: =IFERROR(VLOOKUP(B107,[2]PESOS!A$2:D$3072,4,0),0) -> 0 | N107: =+M107*C107 -> 0
D108: =IFERROR(VLOOKUP(B108,'TARIFA MASTER'!$B$5:$C$3741,2,0),0) -> 0 | E108: =IFERROR(VLOOKUP(B108,'TARIFA MASTER'!B13:L3513,3,0),0) -> 0 | F108: =IFERROR(VLOOKUP(B108,'TARIFA MASTER'!$B$15:$E$3702,4,0),0) -> 0 | G108: =IFERROR(VLOOKUP(B108,'TARIFA MASTER'!$B$5:$L$4699,11,0),0) -> 0 | H108: =IFERROR(VLOOKUP(B108,'TARIFA MASTER'!$B$5:$J$3754,5,0),0) -> 0 | K108: =IFERROR(VLOOKUP(B108,'TARIFA MASTER'!$B$5:$G$3752,6,0),0) -> 0 | L108: =+G108*C108 -> 0 | M108: =IFERROR(VLOOKUP(B108,[2]PESOS!A$2:D$3072,4,0),0) -> 0 | N108: =+M108*C108 -> 0
...

Sheet TARIFA MASTER
C1: REFUERZO | D1: ACC | E1: WHALL PANEL | F1: PISOS | G1: ZOCALOS | H1: CIELO RASO | J1: TUBULARES | N1: TUBULARES
B2: ='PLANILLA PEDIDO'!C3 -> 0 | C2: ='PLANILLA PEDIDO'!C4 -> 0 | D2: ='PLANILLA PEDIDO'!C5 -> 0 | E2: ='PLANILLA PEDIDO'!E3 -> 0 | F2: ='PLANILLA PEDIDO'!G3 -> 0 | G2: ='PLANILLA PEDIDO'!G5 -> 0 | H2: ='PLANILLA PEDIDO'!E4 -> 0 | J2: ='PLANILLA PEDIDO'!E5 -> 0 | K2: 0.05 | N2: 0
B4: Codigo | C4: DESCRIPCIÓN PERFILES PRINCIPALES | D4: Masa | E4: Folio | F4: UNIDAD | G4: PRESENTACIÓN | I4: p unt /ml | J4: FACTURACIÓN u$s | K4: u$d | L4: U$D DESC
B5: 413231000 | C5: Contravidrio ECO | D5: BLANCA | E5: BLANCO | F5: 1 | G5: Paq x 10 unid | H5: 5.8 | I5: =J5/10/5.8 -> 0.32571724 | J5: 18.8916 | K5: =J5 -> 18.8916 | L5: =+J5-K5*$B$2 -> 18.8916 | N5: 18.165 | O5: =N5*1.04 -> 18.8916
B6: 413241000 | C6: Contravidrio DVH ECO | D6: BLANCA | E6: BLANCO | F6: 1 | G6: Paq x 10 unid | H6: 5.8 | I6: =J6/10/5.8 -> 0.23323836 | J6: 13.527825 | K6: =J6 -> 13.527825 | L6: =+J6-K6*$B$2 -> 13.527825 | N6: 13.007524 | O6: =N6*1.04 -> 13.527825
B7: 610281000 | C7: Hoja ECO | D7: BLANCA | E7: BLANCO | F7: 6 | G7: tira | H7: 5.8 | I7: =J7/H7 -> 1.9505379 | J7: 11.31312 | K7: =J7 -> 11.31312 | L7: =+J7-K7*$B$2 -> 11.31312 | N7: 10.878 | O7: =N7*1.04 -> 11.31312
B8: 610291000 | C8: Hoja Guillotina | D8: BLANCA | E8: BLANCO | F8: 6 | G8: tira | H8: 5.8 | I8: =J8/H8 -> 2.1463448 | J8: 12.4488 | K8: =J8 -> 12.4488 | L8: =+J8-K8*$B$2 -> 12.4488 | N8: 11.97 | O8: =N8*1.04 -> 12.4488
B9: 611031000 | C9: Poste Movil ECO | D9: BLANCA | E9: BLANCO | F9: 1 | G9: tira | H9: 5.8 | I9: =J9/H9 -> 2.4794684 | J9: 14.380917 | K9: =J9 -> 14.380917 | L9: =+J9-K9*$B$2 -> 14.380917 | N9: 13.827804 | O9: =N9*1.04 -> 14.380917
B10: 611041000 | C10: Poste Fijo ECO | D10: BLANCA | E10: BLANCO | F10: 4 | G10: tira | H10: 5.8 | I10: =J10/H10 -> 2.4833586 | J10: 14.40348 | K10: =J10 -> 14.40348 | L10: =+J10-K10*$B$2 -> 14.40348 | N10: 13.8495 | O10: =N10*1.04 -> 14.40348
B11: 612381000 | C11: Marco ECO sin Aleta | D11: BLANCA | E11: BLANCO | F11: 4 | G11: tira | H11: 5.8 | I11: =J11/H11 -> 4.1891379 | J11: 24.297 | K11: =J11 -> 24.297 | L11: =+J11-K11*$B$2 -> 24.297 | N11: 23.3625 | O11: =N11*1.04 -> 24.297
B12: 613091000 | C12: Guia ECO BCO | D12: BLANCA | E12: BLANCO | F12: 10 | G12: tira | H12: 5.8 | I12: =J12/H12 -> 0.98844828 | J12: 5.733 | K12: =J12 -> 5.733 | L12: =+J12-K12*$B$2 -> 5.733 | N12: 5.5125 | O12: =N12*1.04 -> 5.733
B13: 612371000 | C13: Marco ECO con Aleta | D13: BLANCA | E13: BLANCO | F13: 4 | G13: tira | H13: 5.8 | I13: =J13/H13 -> 4.3981241 | J13: 25.50912 | K13: =J13 -> 25.50912 | L13: =+J13-K13*$B$2 -> 25.50912 | N13: 24.528 | O13: =N13*1.04 -> 25.50912
B14: 613081000 | C14: Cover Eco | D14: BLANCA | E14: BLANCO | F14: 10 | G14: tira | H14: 5.8 | I14: =+J14/5.8 -> 0.99033103 | J14: 5.74392 | K14: =J14 -> 5.74392 | L14: =+J14-K14*$B$2 -> 5.74392 | N14: 5.523 | O14: =N14*1.04 -> 5.74392
B15: 612161000 | C15: Marco MiniSlide | D15: BLANCA | E15: SIN FOLIO | F15: 1 | G15: tira | H15: 5.8 | I15: =J15/H15 -> 3.149517 | J15: 18.267199 | K15: =J15 -> 18.267199 | L15: =+J15-K15*$B$2 -> 18.267199 | N15: 17.564614 | O15: =N15*1.04 -> 18.267199
B16: 612162000 | C16: Marco MiniSlide | D16: MARFIL | E16: SIN FOLIO | F16: 1 | G16: tira | H16: 5.8 | I16: =J16/H16 -> 3.0224448 | J16: 17.53018 | K16: =J16 -> 17.53018 | L16: =+J16-K16*$B$2 -> 17.53018 | N16: 16.855942 | O16: =N16*1.04 -> 17.53018
B17: 612164013 | C17: Marco MiniSlide | D17: MARFIL | E17: GOLDEN OAK | F17: 1 | G17: tira | H17: 5.8 | I17: =J17/H17 -> 6.1619061 | J17: 35.739055 | K17: =J17 -> 35.739055 | L17: =+J17-K17*$B$2 -> 35.739055 | N17: 34.364476 | O17: =N17*1.04 -> 35.739055
B18: 612163093 | C18: Marco MiniSlide | D18: GRIS | E18: GRIS METALIZADO | F18: 1 | G18: tira | H18: 5.8 | I18: =J18/H18 -> 6.6244283 | J18: 38.421684 | K18: =J18 -> 38.421684 | L18: =+J18-K18*$B$2 -> 38.421684 | N18: 36.943927 | O18: =N18*1.04 -> 38.421684
B19: 612164103 | C19: Marco MiniSlide | D19: MARRON | E19: NOGAL | F19: 1 | G19: tira | H19: 5.8 | I19: =J19/H19 -> 6.1619061 | J19: 35.739055 | K19: =J19 -> 35.739055 | L19: =+J19-K19*$B$2 -> 35.739055 | N19: 34.364476 | O19: =N19*1.04 -> 35.739055
B20: 612162143 | C20: Marco MiniSlide | D20: MARFIL | E20: PELTRE | F20: 1 | G20: tira | H20: 5.8 | I20: =J20/H20 -> 6.652232 | J20: 38.582946 | K20: =J20 -> 38.582946 | L20: =+J20-K20*$B$2 -> 38.582946 | N20: 37.098986 | O20: =N20*1.04 -> 38.582946
B21: 612163283 | C21: Marco MiniSlide | D21: GRIS | E21: JET BLACK | F21: 1 | G21: tira | H21: 5.8 | I21: =J21/H21 -> 7.9705641 | J21: 46.229272 | K21: =J21 -> 46.229272 | L21: =+J21-K21*$B$2 -> 46.229272 | N21: 44.451223 | O21: =N21*1.04 -> 46.229272
B22: 612165283 | C22: Marco MiniSlide | D22: NEGRA | E22: JET BLACK | F22: 1 | G22: tira | H22: 5.8 | I22: =J22/H22 -> 7.9705641 | J22: 46.229272 | K22: =J22 -> 46.229272 | L22: =+J22-K22*$B$2 -> 46.229272 | N22: 44.451223 | O22: =N22*1.04 -> 46.229272
B23: 612165413 | C23: Marco MiniSlide | D23: NEGRA | E23: Matex Kitami | F23: 1 | G23: tira | H23: 5.8 | I23: =J23/H23 -> 8.3026709 | J23: 48.155491 | K23: =J23 -> 48.155491 | L23: =+J23-K23*$B$2 -> 48.155491 | N23: 46.303357 | O23: =N23*1.04 -> 48.155491
B24: 612162243 | C24: Marco MiniSlide | D24: MARFIL | E24: TURNER OAK | F24: 1 | G24: tira | H24: 5.8 | I24: =J24/H24 -> 8.0891965 | J24: 46.91734 | K24: =J24 -> 46.91734 | L24: =+J24-K24*$B$2 -> 46.91734 | N24: 45.112826 | O24: =N24*1.04 -> 46.91734
B25: 612164183 | C25: Marco MiniSlide | D25: MARRON | E25: LENGA | F25: 1 | G25: tira | H25: 5.8 | I25: =J25/H25 -> 7.0942836 | J25: 41.146845 | K25: =J25 -> 41.146845 | L25: =+J25-K25*$B$2 -> 41.146845 | N25: 36.926192 | O25: =N25*1.04 -> 38.40324
B26: 612163113 | C26: Marco MiniSlide | D26: GRIS | E26: GRIS GRAFITO | F26: 1 | G26: tira | H26: 5.8 | I26: =J26/H26 -> 6.1953823 | J26: 35.933217 | K26: =J26 -> 35.933217 | L26: =+J26-K26*$B$2 -> 35.933217 | N26: 34.551171 | O26: =N26*1.04 -> 35.933217
... B32: 610155280 | C32: Hoja MiniSlide | D32: NEGRA | E32: JET BLACK | F32: 1 | G32: tira | H32: 5.8 | I32: =J32/H32 -> 6.9661262 | J32: 40.403532 | K32: =J32 -> 40.403532 | L32: =+J32-K32*$B$2 -> 40.403532 | N32: 38.84955 | O32: =N32*1.04 -> 40.403532
B33: 610155070 | C33: Hoja MiniSlide | D33: NEGRA | E33: Black Matt | F33: 1 | G33: tira | H33: 5.8 | I33: =J33/H33 -> 6.4745487 | J33: 37.552383 | K33: =J33 -> 37.552383 | L33: =+J33-K33*$B$2 -> 37.552383
B34: 610155410 | C34: Hoja MiniSlide | D34: NEGRA | E34: Matex Kitami | F34: 1 | G34: tira | H34: 5.8 | I34: =J34/H34 -> 7.1827865 | J34: 41.660162 | K34: =J34 -> 41.660162 | L34: =+J34-K34*$B$2 -> 41.660162 | N34: 40.057848 | O34: =N34*1.04 -> 41.660162
B35: 612165073 | C35: Marco MiniSlide BLACK MATT | D35: NEGRA | E35: Black Matt | F35: 1 | G35: tira | H35: 5.8 | I35: =J35/H35 -> 6.873227 | J35: 39.864717 | K35: =J35 -> 39.864717 | L35: =+J35-K35*$B$2 -> 39.864717
B36: 610152240 | C36: Hoja MiniSlide | D36: MARFIL | E36: TURNER OAK | F36: 1 | G36: tira | H36: 5.8 | I36: =J36/H36 -> 7.8587519 | J36: 45.580761 | K36: =J36 -> 45.580761 | L36: =+J36-K36*$B$2 -> 45.580761 | N36: 43.827655 | O36: =N36*1.04 -> 45.580761
B37: 610151370 | C37: Hoja MiniSlide | D37: BLANCA | E37: ALPINE | F37: 1 | G37: tira | H37: 5.8 | I37: =J37/H37 -> 7.1520631 | J37: 41.481966 | K37: =J37 -> 41.481966 | L37: =+J37-K37*$B$2 -> 41.481966 | N37: 39.886506 | O37: =N37*1.04 -> 41.481966
B38: 610154360 | C38: Hoja MiniSlide | D38: MARRON | E38: TOFFE | F38: 1 | G38: tira | H38: 5.8 | I38: =J38/H38 -> 7.1520631 | J38: 41.481966 | K38: =J38 -> 41.481966 | L38: =+J38-K38*$B$2 -> 41.481966 | N38: 39.886506 | O38: =N38*1.04 -> 41.481966
B39: 610154390 | C39: Hoja MiniSlide | D39: MARRON | E39: GOLDBRONZE | F39: 1 | G39: tira | H39: 5.8 | I39: =J39/H39 -> 7.5656257 | J39: 43.880629 | K39: =J39 -> 43.880629 | L39: =+J39-K39*$B$2 -> 43.880629 | N39: 42.192912 | O39: =N39*1.04 -> 43.880629
B40: 610154180 | C40: Hoja MiniSlide | D40: MARRON | E40: LENGA | F40: 1 | G40: tira | H40: 5.8 | I40: =J40/H40 -> 6.848717 | J40: 39.722559 | K40: =J40 -> 39.722559 | L40: =+J40-K40*$B$2 -> 39.722559 | N40: 33.783543 | O40: =N40*1.04 -> 35.134884
B41: 610153110 | C41: Hoja MiniSlide | D41: GRIS | E41: GRIS GRAFITO | F41: 1 | G41: tira | H41: 5.8 | I41: =J41/H41 -> 5.7042399 | J41: 33.084591 | K41: =J41 -> 33.084591 | L41: =+J41-K41*$B$2 -> 33.084591 | N41: 31.812107 | O41: =N41*1.04 -> 33.084591
B42: 610153520 | C42: Hoja MiniSlide | D42: GRIS | E42: WHITE ALUM | F42: 1 | G42: tira | H42: 5.8 | I42: =J42/H42 -> 6.6732151 | J42: 38.704647 | K42: =J42 -> 38.704647 | L42: =+J42-K42*$B$2 -> 38.704647 | N42: 37.216007 | O42: =N42*1.04 -> 38.704647
B43: 610155050 | C43: Hoja MiniSlide | D43: NEGRA | E43: Umbra grau | F43: 1 | G43: tira | H43: 5.8 | I43: =J43/H43 -> 6.9662069 | J43: 40.404 | K43: =J43 -> 40.404 | L43: =+J43-K43*$B$2 -> 40.404 | N43: 38.85 | O43: =N43*1.04 -> 40.404
B44: 613031000 | C44: Encuentro MiniSlide | D44: BLANCA | E44: SIN FOLIO | F44: 10 | G44: tira | H44: 5.8 | I44: =J44/H44 -> 0.80130005 | J44: 4.6475403 | K44: =J44 -> 4.6475403 | L44: =+J44-K44*$B$2 -> 4.6475403 | N44: 4.4687887 | O44: =N44*1.04 -> 4.6475403
B45: 613032000 | C45: Encuentro MiniSlide | D45: MARFIL | E45: SIN FOLIO | F45: 10 | G45: tira | H45: 5.8 | I45: =J45/H45 -> 0.84458631 | J45: 4.8986006 | K45: =J45 -> 4.8986006 | L45: =+J45-K45*$B$2 -> 4.8986006 | N45: 4.7101929 | O45: =N45*1.04 -> 4.8986006
B46: 613034010 | C46: Encuentro MiniSlide | D46: MARRON | E46: GOLDEN OAK | F46: 10 | G46: tira | H46: 5.8 | I46: =J46/H46 -> 1.2989009 | J46: 7.5336251 | K46: =J46 -> 7.5336251 | L46: =+J46-K46*$B$2 -> 7.5336251 | N46: 7.2438703 | O46: =N46*1.04 -> 7.5336251
B47: 613033090 | C47: Encuentro MiniSlide | D47: GRIS | E47: GRIS METALIZADO | F47: 10 | G47: tira | H47: 5.8 | I47: =J47/H47 -> 1.4210064 | J47: 8.2418371 | K47: =J47 -> 8.2418371 | L47: =+J47-K47*$B$2 -> 8.2418371 | N47: 7.9248433 | O47: =N47*1.04 -> 8.2418371
... B50: 613035280 | C50: Encuentro MiniSlide | D50: NEGRA | E50: JET BLACK | F50: 10 | G50: tira | H50: 5.8 | I50: =J50/H50 -> 1.7283265 | J50: 10.024294 | K50: =J50 -> 10.024294 | L50: =+J50-K50*$B$2 -> 10.024294 | N50: 9.6387439 | O50: =N50*1.04 -> 10.024294
B51: 613035070 | C51: Encuentro MiniSlide | D51: NEGRA | E51: Black Matt | F51: 10 | G51: tira | H51: 5.8 | I51: =J51/H51 -> 1.8844599 | J51: 10.929867 | K51: =J51 -> 10.929867 | L51: =+J51-K51*$B$2 -> 10.929867
B52: 613035410 | C52: Encuentro MiniSlide | D52: NEGRA | E52: Matex Kitami | F52: 10 | G52: tira | H52: 5.8 | I52: =J52/H52 -> 1.8929181 | J52: 10.978925 | K52: =J52 -> 10.978925 | L52: =+J52-K52*$B$2 -> 10.978925 | N52: 10.556659 | O52: =N52*1.04 -> 10.978925
B53: 613032240 | C53: Encuentro MiniSlide | D53: MARFIL | E53: TURNER OAK | F53: 10 | G53: tira | H53: 5.8 | I53: =J53/H53 -> 1.9564558 | J53: 11.347443 | K53: =J53 -> 11.347443 | L53: =+J53-K53*$B$2 -> 11.347443 | N53: 10.911003 | O53: =N53*1.04 -> 11.347443
B54: 613031370 | C54: Encuentro MiniSlide | D54: BLANCA | E54: ALPINE | F54: 10 | G54: tira | H54: 5.8 | I54: =J54/H54 -> 8.2864425 | J54: 48.061367 | K54: =J54 -> 48.061367 | L54: =+J54-K54*$B$2 -> 48.061367 | N54: 46.212853 | O54: =N54*1.04 -> 48.061367
B55: 613034360 | C55: Encuentro MiniSlide | D55: MARRON | E55: TOFFE | F55: 10 | G55: tira | H55: 5.8 | I55: =J55/H55 -> 1.895353 | J55: 10.993048 | K55: =J55 -> 10.993048 | L55: =+J55-K55*$B$2 -> 10.993048 | N55: 10.570238 | O55: =N55*1.04 -> 10.993048
B56: 613034390 | C56: Encuentro MiniSlide | D56: MARRON | E56: GOLDBRONZE | F56: 10 | G56: tira | H56: 5.8 | I56: =J56/H56 -> 2.0275209 | J56: 11.759621 | K56: =J56 -> 11.759621 | L56: =+J56-K56*$B$2 -> 11.759621 | N56: 11.307328 | O56: =N56*1.04 -> 11.759621
B57: 613034180 | C57: Encuentro MiniSlide | D57: MARRON | E57: LENGA | F57: 10 | G57: tira | H57: 5.8 | I57: =J57/H57 -> 1.8769563 | J57: 10.886347 | K57: =J57 -> 10.886347 | L57: =+J57-K57*$B$2 -> 10.886347 | N57: 7.2438703 | O57: =N57*1.04 -> 7.5336251
B58: 613033110 | C58: Encuentro MiniSlide | D58: GRIS | E58: GRIS GRAFITO | F58: 10 | G58: tira | H58: 5.8 | I58: =J58/H58 -> 1.3412832 | J58: 7.7794424 | K58: =J58 -> 7.7794424 | L58: =+J58-K58*$B$2 -> 7.7794424 | N58: 7.4802331 | O58: =N58*1.04 -> 7.7794424
B59: 613033520 | C59: Encuentro MiniSlide | D59: NEGRA | E59: WHITE ALUM | F59: 10 | G59: tira | H59: 5.8 | I59: =J59/H59 -> 1.909688 | J59: 11.076191 | K59: =J59 -> 11.076191 | L59: =+J59-K59*$B$2 -> 11.076191 | N59: 10.650183 | O59: =N59*1.04 -> 11.076191
B60: 613035050 | C60: Encuentro EuroLife NEG UMBRA | D60: NEGRA | E60: Umbra grau | F60: 10 | G60: tira | H60: 5.8 | I60: =J60/H60 -> 1.9656 | J60: 11.40048 | K60: =J60 -> 11.40048 | L60: =+J60-K60*$B$2 -> 11.40048 | N60: 10.962 | O60: =N60*1.04 -> 11.40048
B61: 112421000 | C61: Marco Advance 2 guias | D61: BLANCO | E61: SIN FOLIO | F61: 1 | G61: Tira | H61: 5.8 | I61: =J61/H61 -> 5.6515782 | J61: 32.779153 | K61: =J61 -> 32.779153 | L61: =+J61-K61*$B$2 -> 32.779153 | N61: 31.518417 | O61: =N61*1.04 -> 32.779153
B62: 112422000 | C62: Marco Advance 2 guias | D62: MARFIL | E62: SIN FOLIO | F62: 1 | G62: Tira | H62: 5.8 | I62: =J62/H62 -> 5.6515782 | J62: 32.779153 | K62: =J62 -> 32.779153 | L62: =+J62-K62*$B$2 -> 32.779153 | N62: 31.518417 | O62: =N62*1.04 -> 32.779153
B63: 112424013 | C63: Marco Advance 2 guias | D63: MARRÓN | E63: GOLDEN OAK | F63: 1 | G63: Tira | H63: 5.8 | I63: =J63/H63 -> 8.9399356 | J63: 51.851627 | K63: =J63 -> 51.851627 | L63: =+J63-K63*$B$2 -> 51.851627 | N63: 49.857333 | O63: =N63*1.04 -> 51.851627
... B67: 112422143 | C67: Marco Advance 2 guias | D67: MARFIL | E67: PELTRE | F67: 1 | G67: Tira | H67: 5.8 | I67: =J67/H67 -> 9.3796046 | J67: 54.401707 | K67: =J67 -> 54.401707 | L67: =+J67-K67*$B$2 -> 54.401707 | N67: 52.309333 | O67: =N67*1.04 -> 54.401707
B68: 112425073 | C68: Marco Advance BLACK MATT | D68: NEGRA | E68: Black Matt | F68: 1 | G68: tira | H68: 5.8 | I68: =J68/H68 -> 10.064736 | J68: 58.375471 | K68: =J68 -> 58.375471 | L68: =+J68-K68*$B$2 -> 58.375471
B69: 112424273 | C69: Marco Advance 2 guias | D69: MARRON | E69: GREY OAK | F69: 1 | G69: Tira | H69: 5.8 | I69: =J69/H69 -> 8.9399356 | J69: 51.851627 | K69: =J69 -> 51.851627 | L69: =+J69-K69*$B$2 -> 51.851627 | N69: 49.857333 | O69: =N69*1.04 -> 51.851627
B70: 112423283 | C70: Marco Advance 2 guias | D70: GRIS | E70: JET BLACK | F70: 1 | G70: Tira | H70: 5.8 | I70: =J70/H70 -> 9.7017354 | J70: 56.270065 | K70: =J70 -> 56.270065 | L70: =+J70-K70*$B$2 -> 56.270065 | N70: 54.105832 | O70: =N70*1.04 -> 56.270065
B71: 112425283 | C71: Marco Advance 2 guias | D71: NEGRA | E71: JET BLACK | F71: 1 | G71: Tira | H71: 5.8 | I71: =J71/H71 -> 9.7017354 | J71: 56.270065 | K71: =J71 -> 56.270065 | L71: =+J71-K71*$B$2 -> 56.270065 | N71: 54.105832 | O71: =N71*1.04 -> 56.270065
B72: 112425413 | C72: Marco Advance 2 guias | D72: NEGRA | E72: Matex Kitami | F72: 1 | G72: tira | H72: 5.8 | I72: =J72/H72 -> 11.546655 | J72: 66.970598 | K72: =J72 -> 66.970598 | L72: =+J72-K72*$B$2 -> 66.970598 | N72: 64.394806 | O72: =N72*1.04 -> 66.970598
B73: 112421373 | C73: Marco Advance 2 guias | D73: MARFIL | E73: ALPINE | F73: 1 | G73: tira | H73: 5.8 | I73: =J73/H73 -> 11.545878 | J73: 66.966092 | K73: =J73 -> 66.966092 | L73: =+J73-K73*$B$2 -> 66.966092 | N73: 64.390473 | O73: =N73*1.04 -> 66.966092
B74: 112424363 | C74: Marco Advance 2 guias | D74: MARRON | E74: TOFFE | F74: 1 | G74: tira | H74: 5.8 | I74: =J74/H74 -> 11.21642 | J74: 65.055234 | K74: =J74 -> 65.055234 | L74: =+J74-K74*$B$2 -> 65.055234 | N74: 62.553109 | O74: =N74*1.04 -> 65.055234
B75: 112424393 | C75: Marco Advance 2 guias | D75: MARRON | E75: GOLDBRONZE | F75: 1 | G75: tira | H75: 5.8 | I75: =J75/H75 -> 11.933446 | J75: 69.213984 | K75: =J75 -> 69.213984 | L75: =+J75-K75*$B$2 -> 69.213984 | N75: 66.551908 | O75: =N75*1.04 -> 69.213984
B76: 112422243 | C76: Marco Advance 2 guias | D76: MARFIL | E76: TURNER OAK | F76: 1 | G76: tira | H76: 5.8 | I76: =J76/H76 -> 11.345291 | J76: 65.802689 | K76: =J76 -> 65.802689 | L76: =+J76-K76*$B$2 -> 65.802689 | N76: 63.271817 | O76: =N76*1.04 -> 65.802689
B77: 112424183 | C77: Marco Advance 2 guias | D77: MARRÓN | E77: LENGA | F77: 1 | G77: tira | H77: 5.8 | I77: =J77/H77 -> 10.521279 | J77: 61.023418 | K77: =J77 -> 61.023418 | L77: =+J77-K77*$B$2 -> 61.023418 | N77: 49.857333 | O77: =N77*1.04 -> 51.851627
B78: 112423523 | C78: Marco Advance 2 guias | D78: GRIS | E78: WHITE ALUM | F78: 1 | G78: tira | H78: 5.8 | I78: =J78/H78 -> 10.300135 | J78: 59.740781 | K78: =J78 -> 59.740781 | L78: =+J78-K78*$B$2 -> 59.740781 | N78: 57.443059 | O78: =N78*1.04 -> 59.740781
B79: 112425053 | C79: Marco Advance 2 guias | D79: NEGRA | E79: Umbra grau | F79: 1 | G79: tira | H79: 5.8 | I79: =J79/H79 -> 10.801386 | J79: 62.64804 | K79: =J79 -> 62.64804 | L79: =+J79-K79*$B$2 -> 62.64804 | N79: 60.2385 | O79: =N79*1.04 -> 62.64804
B80: 112431000C | C80: Marco Advance 3 guías BCO CAJON x 84 unidades | D80: BLANCO | E80: SIN FOLIO | F80: 1 | G80: CAJON | H80: 5.8 | I80: =J80/H80 -> 748.64633 | J80: 4342.1487 | K80: =J80 -> 4342.1487 | L80: =+J80-K80*$B$2 -> 4342.1487 | N80: 4175.143 | O80: =N80*1.04 -> 4342.1487
B81: 112431000 | C81: Marco Advance 3 guías | D81: BLANCO | E81: SIN FOLIO | F81: 1 | G81: Tira | H81: 5.8 | I81: =J81/H81 -> 8.9124563 | J81: 51.692247 | K81: =J81 -> 51.692247 | L81: =+J81-K81*$B$2 -> 51.692247 | N81: 49.704083 | O81: =N81*1.04 -> 51.692247
B82: 112432000 | C82: Marco Advance 3 guías | D82: MARFIL | E82: SIN FOLIO | F82: 1 | G82: Tira | H82: 5.8 | I82: =J82/H82 -> 8.9124563 | J82: 51.692247 | K82: =J82 -> 51.692247 | L82: =+J82-K82*$B$2 -> 51.692247 | N82: 49.704083 | O82: =N82*1.04 -> 51.692247
B83: 112434013 | C83: Marco Advance 3 guías | D83: MARRON | E83: GOLDEN OAK | F83: 1 | G83: Tira | H83: 5.8 | I83: =J83/H83 -> 15.818923 | J83: 91.749753 | K83: =J83 -> 91.749753 | L83: =+J83-K83*$B$2 -> 91.749753 | N83: 88.220917 | O83: =N83*1.04 -> 91.749753
B84: 112433093 | C84: Marco Advance 3 guías | D84: GRIS | E84: GRIS METALIZADO | F84: 1 | G84: Tira | H84: 5.8 | I84: =J84/H84 -> 15.818923 | J84: 91.749753 | K84: =J84 -> 91.749753 | L84: =+J84-K84*$B$2 -> 91.749753 | N84: 88.220917 | O84: =N84*1.04 -> 91.749753
B85: 112434103 | C85: Marco Advance 3 guías | D85: MARRON | E85: NOGAL | F85: 1 | G85: Tira | H85: 5.8 | I85: =J85/H85 -> 15.818923 | J85: 91.749753 | K85: =J85 -> 91.749753 | L85: =+J85-K85*$B$2 -> 91.749753 | N85: 88.220917 | O85: =N85*1.04 -> 91.749753
B86: 112433113 | C86: Marco Advance 3 guías | D86: GRIS | E86: GRIS GRAFITO | F86: 1 | G86: Tira | H86: 5.8 | I86: =J86/H86 -> 15.818923 | J86: 91.749753 | K86: =J86 -> 91.749753 | L86: =+J86-K86*$B$2 -> 91.749753 | N86: 88.220917 | O86: =N86*1.04 -> 91.749753
B87: 112432143 | C87: Marco Advance 3 guías | D87: MARFIL | E87: PELTRE | F87: 1 | G87: Tira | H87: 5.8 | I87: =J87/H87 -> 15.818923 | J87: 91.749753 | K87: =J87 -> 91.749753 | L87: =+J87-K87*$B$2 -> 91.749753 | N87: 88.220917 | O87: =N87*1.04 -> 91.749753
B88: 112434273 | C88: Marco Advance 3 guías | D88: MARRON | E88: GREY OAK | F88: 1 | G88: Tira | H88: 5.8 | I88: =J88/H88 -> 15.818923 | J88: 91.749753 | K88: =J88 -> 91.749753 | L88: =+J88-K88*$B$2 -> 91.749753 | N88: 88.220917 | O88: =N88*1.04 -> 91.749753
B89: 112433283 | C89: Marco Advance 3 guías | D89: GRIS | E89: JET BLACK | F89: 1 | G89: Tira | H89: 5.8 | I89: =J89/H89 -> 16.704783 | J89: 96.88774 | K89: =J89 -> 96.88774 | L89: =+J89-K89*$B$2 -> 96.88774 | N89: 93.161288 | O89: =N89*1.04 -> 96.88774
B90: 112435073 | C90: Marco Advance 3 guías BLACK MATT | D90: NEGRA | E90: Black Matt | F90: 1 | G90: tira | H90: 5.8 | I90: =J90/H90 -> 14.935725 | J90: 86.627202 | K90: =J90 -> 86.627202 | L90: =+J90-K90*$B$2 -> 86.627202
B91: 112435413 | C91: Marco Advance 3 guías | D91: NEGRA | E91: Matex Kitami | F91: 1 | G91: tira | H91: 5.8 | I91: =J91/H91 -> 16.875909 | J91: 97.880271 | K91: =J91 -> 97.880271 | L91: =+J91-K91*$B$2 -> 97.880271 | N91: 94.115645 | O91: =N91*1.04 -> 97.880271
B92: 112431373 | C92: Marco Advance 3 guías | D92: MARFIL | E92: ALPINE | F92: 1 | G92: tira | H92: 5.8 | I92: =J92/H92 -> 18.318497 | J92: 106.24728 | K92: =J92 -> 106.24728 | L92: =+J92-K92*$B$2 -> 106.24728 | N92: 102.16085 | O92: =N92*1.04 -> 106.24728
B93: 112434363 | C93: Marco Advance 3 guías | D93: MARRON | E93: TOFFE | F93: 1 | G93: tira | H93: 5.8 | I93: =J93/H93 -> 16.428288 | J93: 95.284073 | K93: =J93 -> 95.284073 | L93: =+J93-K93*$B$2 -> 95.284073 | N93: 91.619301 | O93: =N93*1.04 -> 95.284073
B94: 112434393 | C94: Marco Advance 3 guías | D94: MARRON | E94: GOLDBRONZE | F94: 1 | G94: tira | H94: 5.8 | I94: =J94/H94 -> 17.387581 | J94: 100.84797 | K94: =J94 -> 100.84797 | L94: =+J94-K94*$B$2 -> 100.84797 | N94: 96.969204 | O94: =N94*1.04 -> 100.84797
B95: 112435283 | C95: Marco Advance 3 guías | D95: NEGRA | E95: JET BLACK | F95: 1 | G95: Tira | H95: 5.8 | I95: =J95/H95 -> 16.704783 | J95: 96.88774 | K95: =J95 -> 96.88774 | L95: =+J95-K95*$B$2 -> 96.88774 | N95: 93.161288 | O95: =N95*1.04 -> 96.88774
B96: 112432243 | C96: Marco Advance 3 guías | D96: MARFIL | E96: TURNER OAK | F96: 1 | G96: tira | H96: 5.8 | I96: =J96/H96 -> 19.133844 | J96: 110.97629 | K96: =J96 -> 110.97629 | L96: =+J96-K96*$B$2 -> 110.97629 | N96: 106.70798 | O96: =N96*1.04 -> 110.97629
B97: 112434183 | C97: Marco Advance 3 guías | D97: MARRÓN | E97: LENGA | F97: 1 | G97: tira | H97: 5.8 | I97: =J97/H97 -> 15.355902 | J97: 89.064231 | K97: =J97 -> 89.064231 | L97: =+J97-K97*$B$2 -> 89.064231 | N97: 88.220917 | O97: =N97*1.04 -> 91.749753
B98: 112433523 | C98: Marco Advance 3 guías | D98: GRIS | E98: WHITE ALUM | F98: 1 | G98: tira | H98: 5.8 | I98: =J98/H98 -> 15.098009 | J98: 87.568451 | K98: =J98 -> 87.568451 | L98: =+J98-K98*$B$2 -> 87.568451 | N98: 84.200434 | O98: =N98*1.04 -> 87.568451
B99: 112435053 | C99: Marco Advance 3 guías | D99: NEGRA | E99: Umbra grau | F99: 1 | G99: tira | H99: 5.8 | I99: =J99/H99 -> 16.078759 | J99: 93.2568 | K99: =J99 -> 93.2568 | L99: =+J99-K99*$B$2 -> 93.2568 | N99: 89.67 | O99: =N99*1.04 -> 93.2568
B100: 112441000 | C100: Marco Movil Fijo Advance | D100: BLANCO | E100: BLANCO | F100: 1 | G100: tira | H100: 5.8 | I100: =J100/H100 -> 6.3500888 | J100: 36.830515 | K100: =J100 -> 36.830515 | L100: =+J100-K100*$B$2 -> 36.830515 | N100: 35.413957 | O100: =N100*1.04 -> 36.830515
B101: 112442000 | C101: Marco Movil Fijo Advance | D101: MARFIL | E101: MARFIL | F101: 1 | G101: tira | H101: 5.8 | I101: =J101/H101 -> 6.1115688 | J101: 35.447099 | K101: =J101 -> 35.447099 | L101: =+J101-K101*$B$2 -> 35.447099 | N101: 34.083749 | O101: =N101*1.04 -> 35.447099
B102: 112444013 | C102: Marco Movil Fijo Advance | D102: MARRÓN | E102: GOLDEN OAK | F102: 1 | G102: tira | H102: 5.8 | I102: =J102/H102 -> 10.662626 | J102: 61.84323 | K102: =J102 -> 61.84323 | L102: =+J102-K102*$B$2 -> 61.84323 | N102: 59.464644 | O102: =N102*1.04 -> 61.84323
... B104: 112445283 | C104: Marco Movil Fijo Advance | D104: NEGRA | E104: JET BLACK | F104: 1 | G104: tira | H104: 5.8 | I104: =J104/H104 -> 13.176232 | J104: 76.422143 | K104: =J104 -> 76.422143 | L104: =+J104-K104*$B$2 -> 76.422143 | N104: 73.48283 | O104: =N104*1.04 -> 76.422143
B105: 112445073 | C105: Marco Movil Fijo Advance | D105: NEGRA | E105: Black Matt | F105: 1 | G105: tira | H105: 5.8 | I105: =J105/H105 -> 10.921325 | J105: 63.343685
B106: 112443093 | C106: Marco Movil Fijo Advance | D106: GRIS | E106: GRIS METALIZADO | F106: 1 | G106: tira | H106: 5.8 | I106: =J106/H106 -> 12.477492 | J106: 72.369454 | K106: =J106 -> 72.369454 | L106: =+J106-K106*$B$2 -> 72.369454 | N106: 69.586013 | O106: =N106*1.04 -> 72.369454
B107: 112444103 | C107: Marco Movil Fijo Advance | D107: MARRÓN | E107: NOGAL | F107: 1 | G107: tira | H107: 5.8 | I107: =J107/H107 -> 10.662626 | J107: 61.84323 | K107: =J107 -> 61.84323 | L107: =+J107-K107*$B$2 -> 61.84323 | N107: 59.464644 | O107: =N107*1.04 -> 61.84323
B108: 112443113 | C108: Marco Movil Fijo Advance | D108: GRIS | E108: GRIS GRAFITO | F108: 1 | G108: tira | H108: 5.8 | I108: =J108/H108 -> 12.477492 | J108: 72.369454 | K108: =J108 -> 72.369454 | L108: =+J108-K108*$B$2 -> 72.369454 | N108: 69.586013 | O108: =N108*1.04 -> 72.369454
B109: 112442143 | C109: Marco Movil Fijo Advance | D109: MARFIL | E109: PELTRE | F109: 1 | G109: tira | H109: 5.8 | I109: =J109/H109 -> 12.477492 | J109: 72.369454 | K109: =J109 -> 72.369454 | L109: =+J109-K109*$B$2 -> 72.369454 | N109: 69.586013 | O109: =N109*1.04 -> 72.369454
B110: 112444273 | C110: Marco Movil Fijo Advance | D110: MARRÓN | E110: GREY OAK | F110: 1 | G110: tira | H110: 5.8 | I110: =J110/H110 -> 10.662626 | J110: 61.84323 | K110: =J110 -> 61.84323 | L110: =+J110-K110*$B$2 -> 61.84323 | N110: 59.464644 | O110: =N110*1.04 -> 61.84323
B111: 112441373 | C111: Marco Movil Fijo Advance | D111: MARFIL | E111: ALPINE | F111: 1 | G111: tira | H111: 5.8 | I111: =J111/H111 -> 12.761952 | J111: 74.01932 | K111: =J111 -> 74.01932 | L111: =+J111-K111*$B$2 -> 74.01932 | N111: 71.172423 | O111: =N111*1.04 -> 74.01932
B112: 112444363 | C112: Marco Movil Fijo Advance | D112: MARRON | E112: TOFFE | F112: 1 | G112: tira | H112: 5.8 | I112: =J112/H112 -> 11.874632 | J112: 68.872866 | K112: =J112 -> 68.872866 | L112: =+J112-K112*$B$2 -> 68.872866 | N112: 66.22391 | O112: =N112*1.04 -> 68.872866
...

Sheet  LAMINA PERFILES

Sheet TUBULAR 58 X 58
B1: PERFIL TUBULAR 58 X 58 mm | G1: =+TODAY() -> 46148
E3: completar solo la parte en verde | G3: ANCHO METROS | H3: ALTO METROS | AD3: PLANILLA PEDIDO
C4: COLOR | E4: LENGA | G4: 4
E5: =E6*10 -> 0
C6: CANTIDAD | E6: 0 | G6: HORIENTACION | H6: vertical
C8: REF CANTIDAD | E8: 0
E9: 0
C11: TAPAS CANT | E11: 41
H13: =#REF!*10 -> #REF!
C14: CODIGO | E14: DESCRIPCION | F14: PRE.UNIT | G14: CANTIDAD | H14: TOTAL
B15: B- | C15: =IFERROR(VLOOKUP(E4,M78:N96,2,0),0) -> 913370180 | E15: Perfil tubular 38 x 76 mm | F15: =VLOOKUP(C15,'TARIFA MASTER'!B15:J3408,9,0) -> 64.109886 | G15: =E6 -> 0 | H15: =+G15*F15 -> 0
B16: C- | C16: 920370015 | E16: refuerzo acero | F16: =IFERROR(VLOOKUP(C16,'[1]TARIFA MASTER'!C$46:K$2442,9,0),0) -> 53.162122 | G16: =E8 -> 0 | H16: =F16*G16 -> 0
C18: =J76 -> 0 | F18: TUBULARES | G18: 0.2 | H18: =H15-(H15*G18) -> 0
F20: REFUERZO | G20: 0 | H20: =H16-(H16*G20) -> 0
F22: REF ALUMINIO | G22: 0 | H22: =IF(#REF!="aluminio",H16-(H16*G22),0) -> #REF!
G25: TOTAL | H25: =SUM(H18+H20) -> 0
M27: ALUMINIO | Q27: 55.56 | R27: 51.3764
C28: A - Los valores están expresados en dólares, no incluyen impuestos | M28: ACERO | Q28: 25 | R28: 66.6101
C30: B - Este cotizador solo contempla tira standard (5800mm) de tubular con refuerzo
C31: * Unidad de embalaje
C32: tubular | E32: por tira 5,8 METROS
C33: refuerzos | E33: por tira 3 METROS
C35: D- Para un cómputo más detallado, se recomienda optimizar su proyecto en Autocad.
C37: E - Los descuentos corresponden a los asignados en PVC /REFUERZO
H45: peso 38 x 38
M78: GOLDEN OAK | N78: 913370010
M79: NATURAL OAK | N79: 913370020
M80: JET BLACK | N80: 913370280
M81: GRIS METALIZADO | N81: 913370090
M82: NOGAL | N82: 913370100
M83: GRIS GRAFITO | N83: 913370110
M84: SCHWARTZBRAUN | N84: 913370120
M85: WENGUE | N85: 913370250
M86: GREY OAK | N86: 913370270
M87: BLANCO ALTWEISSE | N87: 913370380
M88: ALPINE | N88: 913370370
M89: TOFFEE | N89: 913370360
... M96: GEN ALUM | N96: 913370520

Sheet  CIELORRASO EXT
C1: completar solo la parte en verde | E1: =ROUNDUP(D7,0) -> 2 | H1: =ROUNDUP(G7,0) -> 2 | I1: =+TODAY() -> 46148 | L1: =ROUNDUP(J7,0) -> 1
B2: CIELORASO | E2: MOLDURA EN " L " | H2: MOLDURA | I2: =+I4/5.8 -> 15.689655 | K2: UNION CIELO RASO
B3: COLOR | C3: CONCRET_C_ | E3: COLOR | F3: EUCALYPTUS | H3: COLOR | I3: EUCALYPTUS | K3: COLOR | L3: EUCALYPTUS
B4: M² | C4: 12 | E4: CANT ML | F4: 92 | H4: CANT ML | I4: 91 | K4: CANT ML | L4: 20
B5: UN EMB 10 TABLAS de CIELORRASO = 12 M² | E5: UN EMB 30 TIRAS = 90 Mts Lineales | H5: UN EMB 30 TIRAS = 3Mts Lineales x Tira | K5: UN EMB 10 TIRAS = 3Mts Lineales x Tira
A6: =ROUNDUP(A7,0) -> 1
A7: =+C4/12 -> 1 | B7: PAQUETE | C7: =A6 -> 1 | D7: =F4/90 -> 1.0222222 | E7: PAQUETE | F7: =E1 -> 2 | G7: =I4/90 -> 1.0111111 | H7: PAQUETE | I7: =H1 -> 2 | J7: =L4/30 -> 0.66666667 | K7: PAQUETE | L7: =L1 -> 1
A8: =A6*10 -> 10 | B8: TOTAL TABLAS | C8: =A8 -> 10 | D8: =F7*30 -> 60 | E8: TOTAL TIRAS | F8: =D8 -> 60 | G8: =I7*30 -> 60 | H8: TOTAL TIRAS | I8: =G8 -> 60 | J8: =L7*10 -> 10 | K8: TOTAL TIRAS | L8: =J8 -> 10
B10: CODIGO | C10: DESCRIPCION | D10: PRE.UNIT | E10: CANTIDAD | F10: TOTAL
A11: =+#REF!+#REF! -> #REF! | B11: =IFERROR(VLOOKUP(C3,B36:C44,2,0),0) -> 913610500 | C11: CIELO RASO | D11: =IFERROR(VLOOKUP(B11,'[1]TARIFA MASTER'!C$46:K$2442,9,0),0) -> 24 | E11: =C8 -> 10 | F11: =IFERROR((D11*E11),"") -> 240
B12: =VLOOKUP(F3,H36:I43,2,0) -> 913620440 | C12: MOLDURA " L " | D12: =IFERROR(VLOOKUP(B12,'[1]TARIFA MASTER'!C$46:K$2442,9,0),0) -> 4.2376758 | E12: =F8 -> 60 | F12: =IFERROR((D12*E12),"") -> 254.26055
B13: =VLOOKUP(I3,B45:C52,2,0) -> 913630440 | C13: MOLDURA | D13: =IFERROR(VLOOKUP(B13,'[1]TARIFA MASTER'!C$46:K$2442,9,0),0) -> 6.0353594 | E13: =I8 -> 60 | F13: =IFERROR((D13*E13),"") -> 362.12156
B14: =VLOOKUP(L3,H45:I52,2,0) -> 913640440 | C14: UNION CIELO RASO | D14: =IFERROR(VLOOKUP(B14,'[1]TARIFA MASTER'!C$46:K$2442,9,0),0) -> 7.1147245 | E14: =L8 -> 10 | F14: =IFERROR((D14*E14),"") -> 71.147245
E16: SUB TOTAL | F16: =SUM(F11:F14) -> 927.52936 | K16: MOLDURA L | M16: UNION
K17: =ROUNDUP(K29,0) -> 31 | L17: =ROUNDUP(L29,0) -> 31 | M17: =ROUNDUP(M29,0) -> 7
D18: DESC | E18: 0.1 | F18: =(F16*E18) -> 92.752936
E20: TOTAL | F20: =+F16-F18 -> 834.77642
K21: 2606
B26: =I4*10% -> 9.1
K29: =F4/3 -> 30.666667 | L29: =I4/3 -> 30.333333 | M29: =L4/3 -> 6.6666667
A31: A - Los valores están expresados en dólares, no incluyen impuestos
A32: B - Este cotizador solo contempla tira standard (3000 mm Molduras / 6000 mm para CIELO RASO)
A33: C - Para un cómputo más detallado, se recomienda optimizar su proyecto en Autocad.
A34: D- Los descuentos corresponden a los asignados en PVC
B36: BLANCO_ | C36: 913611000 | D36: Cielorraso BCO | H36: BLANCO | I36: 913621000 | J36: Perimetral L BCO
B37: OAK_ | C37: 913610430 | D37: Cielorraso GEN OAK | H37: OAK | I37: 913620430 | J37: Perimetral L GEN OAK
B38: EUCALIPTUS_ | C38: 913610440 | D38: Cieloraso GEN EUC | H38: EUCALYPTUS | I38: 913620440 | J38: Perimetral L GEN EUC
B39: POPLAR_ | C39: 913610450 | D39: Cieloraso GEN POP | H39: POPLAR | I39: 913620450 | J39: Perimetral L GEN POP
B40: WALNUT_ | C40: 913610460 | D40: Cieloraso GEN WAL | H40: WALNUT | I40: 913620460 | J40: Perimetral L GEN WAL
B41: TEAK_ | C41: 913610470 | D41: Cieloraso GEN TEEK | H41: TEEK | I41: 913620470 | J41: Perimetral L GEN TEEK
B42: CONCRET_WITE_ | C42: 913610490 | D42: Cieloraso GEN WCON | H42: WHITE CONCRETE | I42: 913620490 | J42: Perimetral L GEN WCON
B43: CONCRET_C_ | C43: 913610500 | D43: Cieloraso GEN CONC | H43: CONCRETE C | I43: 913620500 | J43: Perimetral L GEN CONC
B45: BLANCO | C45: 913631000 | D45: Perimetral Moldura BCO | H45: BLANCO | I45: 913641000 | J45: Union Cielorraso BCO
B46: OAK | C46: 913630430 | D46: Perimetral Moldura GEN OAK | H46: OAK | I46: 913640430 | J46: Union Cielorraso GEN OAK
B47: EUCALYPTUS | C47: 913630440 | D47: Perimetral Moldura GEN EUC | H47: EUCALYPTUS | I47: 913640440 | J47: Union Cielorraso GEN EUC
B48: POPLAR | C48: 913630450 | D48: Perimetral Moldura GEN POP | H48: POPLAR | I48: 913640450 | J48: Union Cielorraso GEN POP
B49: WALNUT | C49: 913630460 | D49: Perimetral Moldura GEN WAL | H49: WALNUT | I49: 913640460 | J49: Union Cielorraso GEN WAL
... B52: CONCRETE C | C52: 913630500 | D52: Perimetral Moldura GEN CONC | H52: CONCRETE C | I52: 913640500 | J52: Union Cielorraso GEN CONC
C57: 0
C58: 12
C59: 24
C60: 36
C61: 48
C62: 60
C63: 72
C64: 84
C65: 96
C66: 108
C67: 120
C68: 132
... C157: 1200

Sheet PESOS
A1: Codigo | B1: DESCRIPCIÓN PERFILES PRINCIPALES | C1: Presentacion | D1: peso OK
A2: 110101000 | B2: Perfil de PVC Hoja Dz 46-89 BLANCO | C2: tira | D2: 7.74
A3: 110101010 | B3: Perfil de PVC LAMINADO Hoja Dz 46-89 GOLDEN OAK | C3: tira | D3: 8.15
A4: 110101011 | B4: Perfil de PVC LAMINADO Hoja Dz 46-89 GOLDEN OAK | C4: tira | D4: 8
A5: 110101012 | B5: Perfil de PVC LAMINADO Hoja Dz 46-89 GOLDEN OAK | C5: tira | D5: 7.95
A6: 110101020 | B6: Perfil de PVC LAMINADO Hoja Dz 46-89 NATURAL OAK | C6: tira | D6: 8.15
A7: 110101021 | B7: Perfil de PVC LAMINADO Hoja Dz 46-89 NATURAL OAK | C7: tira | D7: 8
A8: 110101022 | B8: Perfil de PVC LAMINADO Hoja Dz 46-89 NATURAL OAK | C8: tira | D8: 7.95
A9: 110101060 | B9: Perfil de PVC LAMINADO Hoja Dz 46-89 VERDE | C9: tira | D9: 8.15
A10: 110101061 | B10: Perfil de PVC LAMINADO Hoja Dz 46-89 VERDE | C10: tira | D10: 8
A11: 110101062 | B11: Perfil de PVC LAMINADO Hoja Dz 46-89 VERDE | C11: tira | D11: 7.95
A12: 110101080 | B12: Perfil de PVC LAMINADO Hoja Dz 46-89 CHERRY | C12: tira | D12: 8.15
A13: 110101081 | B13: Perfil de PVC LAMINADO Hoja Dz 46-89 CHERRY | C13: tira | D13: 8
... A2776: 945705000 | B2776: Adaptador Refuerzo 20x23 mm de plastico | C2776: un | D2776: 0.025
A2777: 01-6061-1Q | B2777: Panel siding doble 4 `` Smoke characol de pvc | C2777: 24 tiras | D2777: 1.78
A2778: 01-6061-3T | B2778: Panel siding doble 4 `` English Saddle de pvc | C2778: 24 tiras | D2778: 1.78
A2779: 01-6061-V7 | B2779: Panel siding doble 4 `` Antique Parchment de pvc | C2779: 24 tiras | D2779: 1.78
A2780: 10-3956-1Q | B2780: PVC Trim Coil Smoke characol 1Q de pvc | C2780: rollo | D2780: 12.72
A2781: 10-3956-3T | B2781: PVC Trim Coil English Saddle 3T de pvc | C2781: rollo | D2781: 12.72
A2782: 10-3956-V7 | B2782: PVC Trim Coil Antique Parchment V7 de pvc | C2782: rollo | D2782: 12.72
A2783: 10-5053-1Q | B2783: Perfil de PVC Esquinero interior Smoke characol | C2783: tira | D2783: 0.99
A2784: 10-5053-V7 | B2784: Perfil de PVC Esquinero interior Antique Parchment | C2784: tira | D2784: 0.99
A2785: 10-5118-1Q | B2785: Perfil de PVC canal J 3/4`` Smoke characol | C2785: tira | D2785: 0.72
A2786: 10-5118-3T | B2786: Perfil de PVC canal J 3/4`` English Saddle | C2786: tira | D2786: 0.72
A2787: 10-5118-V7 | B2787: Perfil de PVC canal J 3/4`` Antique Parchment | C2787: tira | D2787: 0.72
A2788: 10-5200-1Q | B2788: Perfil de PVC de terminacion Smoke characol | C2788: tira | D2788: 0.46
... A2793: 10-5644-3T | B2793: Perfil de PVC Esquinero exterior 4`` English Saddle | C2793: tira | D2793: 2.03
A2794: 10-7361 | B2794: Perfil de inicio 2 1/2`` Galvanizado de acero galvanizado | C2794: tira | D2794: #N/A
A2795: 76-0010 | B2795: Destrabador de paneles Siding PVC - ZIP Tool de metal | C2795: un | D2795: 0.1
A2796: 76-7203 | B2796: Pinza para realizar lengüetas Siding PVC - Snap Lock punch de metal | C2796: un | D2796: 0.3
A2797: 76-8062 | B2797: Tijera especial para Siding PVC – Snip de metal | C2797: un | D2797: 0.44
A2798: B.2400H100B | B2798: Kit marco Blanco 2460 x 100 Blanca de WPC | C2798: un | D2798: 16.5
A2799: B.2400H140B | B2799: Kit marco Blanco 2460 x 140 Blanca de WPC | C2799: un | D2799: 18
A2800: B.2400H180B | B2800: Kit marco Blanco 2460 x 180 Blanca de WPC | C2800: un | D2800: 19
A2801: B.2400H220B | B2801: Kit marco Blanco 2460 x 220 Blanca de WPC | C2801: un | D2801: 20
A2802: B.KA10.900X2050NH7 | B2802: Hoja Lisa Blanca x7mm 900 x 2050 Blanca de WPC | C2802: un | D2802: 38
A2803: B.KL01.700X2050BSH | B2803: Hoja buña Blanca calada 700 X 2050 Blanca de WPC | C2803: un | D2803: 22.5
A2804: B.KL01.800X2050BSH | B2804: Hoja buña Blanca calada 800 X 2050 Blanca de WPC | C2804: un | D2804: 22.5
A2805: B.KL01.800X2400BSH | B2805: Hoja buña Blanca calada 800 X 2400 Blanca de WPC | C2805: un | D2805: 26.3
A2806: B.KL01.900X2050BSH | B2806: Hoja buña Blanca calada 900X 2050 Blanca de WPC | C2806: un | D2806: 26.5
A2807: B.KL01.900X2400BSH | B2807: Hoja buña Blanca calada 900 X 2400 Blanca de WPC | C2807: un | D2807: 31
A2808: B800X2050A140 | B2808: Kit marco Blanco 2180 x 140 x 800 de WPC | D2808: 16.2
A2809: BB800X2050 | B2809: Hoja buña Blanca calada 800 X 2050 de WPC | D2809: 22.5
A2810: CE215650 | B2810: Vierteaguas - de aluminio | C2810: tira | D2810: #N/A
A2811: CE406158 | B2811: Prolongador 20 x 21 mm BLANCO de pvc | C2811: tira | D2811: 2.1
A2812: CE40615800 | B2812: Prolongador 20 x 21 mm GOLDEN OAK de pvc | C2812: tira | D2812: 2.73
A2813: CE40615840 | B2813: Prolongador 20 x 21 mm NOGAL de pvc | C2813: tira | D2813: 2.73
A2814: CE413825 | B2814: Junquillo inclinado con junta 25 mm BLANCO de pvc | C2814: tira | D2814: 1.6
A2815: CE41382500 | B2815: Junquillo inclinado con junta 25 mm GOLDEN OAK de pvc | C2815: tira | D2815: 2.23
A2816: CE41382540 | B2816: Junquillo inclinado con junta 25 mm NOGAL de pvc | C2816: tira | D2816: 2.23
A2817: CE413829 | B2817: Junquillo inclinado con junta 29 mm BLANCO de pvc | C2817: tira | D2817: 1.92
A2818: CE41382900 | B2818: Junquillo inclinado con junta 29 mm GOLDEN OAK de pvc | C2818: tira | D2818: 2.55
A2819: CE41382940 | B2819: Junquillo inclinado con junta 29 mm NOGAL de pvc | C2819: tira | D2819: 2.55
A2820: CE413833 | B2820: Junquillo inclinado con junta 33 mm BLANCO de pvc | C2820: tira | D2820: 1.72
A2821: CE41383300 | B2821: Junquillo inclinado con junta 33 mm GOLDEN OAK de pvc | C2821: tira | D2821: 2.35
A2822: CE41383340 | B2822: Junquillo inclinado con junta 33 mm NOGAL de pvc | C2822: tira | D2822: 2.35
... A2889: N.KA10.900X2400BSH | B2889: Hoja lisa Nogal calada 900 X 2400 Simil Nogal de WPC | C2889: un | D2889: 31
A2890: N700X2050 | B2890: Hoja buña Blanca calada 800 X 2050 de WPC | D2890: #N/A
A2891: N700X2050A100 | B2891: Kit marco Madera 2180 x 100 x 700 de WPC | D2891: 14.8
A2892: PSI/IROKO-P | B2892: Tabla piso sintetico interior x pallet Iroko de pvc | C2892: caja x 2,18 m2 | D2892: 17.4
A2893: PSI/PINOT-P | B2893: Tabla piso sintetico interior x pallet Pinotea de pvc | C2893: caja x 2,18 m2 | D2893: 17.4
A2894: PSI/ROBLE-P | B2894: Tabla piso sintetico interior x pallet Roble de pvc | C2894: caja x 2,18 m2 | D2894: 17.4
A2895: SR08210SB | B2895: Cerradura baño Plateada Platil de acero | C2895: un | D2895: 0.474
A2896: SR08210SS | B2896: Cerradura tradicional plateada Platil de acero | C2896: un | D2896: 0.474
A2897: 913511000 | B2897: Perfil de PVC Zocalo PVC 12x60 Blanco 2900 ml | C2897: Paq x 5 tira | D2897: 1.062
A2898: 913521000 | B2898: Perfil de PVC Zocalo PVC 12x80 Blanco 2900 ml | C2898: Paq x 5 tira | D2898: 0.754
A2899: 913510290 | B2899: Perfil de PVC Laminado Zocalo PVC 12x60 2900 ml Almendra | C2899: Paq x 5 tira | D2899: 0.58
A2900: 913520290 | B2900: Perfil de PVC Laminado Zocalo PVC 12x80 2900 ml Almendra | C2900: Paq x 5 tira | D2900: 0.754
A2901: 913510310 | B2901: Perfil de PVC Laminado Zocalo PVC 12x60 2900 ml Abedul | C2901: Paq x 5 tira | D2901: 0.58
A2902: 913520310 | B2902: Perfil de PVC Laminado Zocalo PVC 12x80 2900 ml Abedul | C2902: Paq x 5 tira | D2902: 0.754
A2903: 110101240 | B2903: Perfil de PVC LAMINADO Hoja Dz 46-89 TURNER OAK MALT | C2903: tira | D2903: 8.24
A2904: 110101241 | B2904: Perfil de PVC LAMINADO Hoja Dz 46-89 TURNER OAK MALT | C2904: tira | D2904: 8.05
A2905: 110101242 | B2905: Perfil de PVC LAMINADO Hoja Dz 46-89 TURNER OAK MALT | C2905: tira | D2905: 7.99
A2906: 110102240 | B2906: Perfil de PVC LAMINADO Hoja Dz 46-89 TURNER OAK MALT | C2906: tira | D2906: 7.84
A2907: 110111240 | B2907: Perfil de PVC LAMINADO Hoja Dz 46-74 TURNER OAK MALT | C2907: tira | D2907: 7.87
A2908: 110111241 | B2908: Perfil de PVC LAMINADO Hoja Dz 46-74 TURNER OAK MALT | C2908: tira | D2908: 7.71
... A3072: 913380240 | B3072: Perfil de PVC LAMINADO Embellecedor Ref 20x23 mm GEN TURNER OAK MALT | C3072: paq x 4 tiras | D3072: 1.69
